[
  {
    "Text": "Yes",
    "StartAddress": 86384,
    "EndAddress": 86391,
    "MaxLength": 8
  },
  {
    "Text": "No",
    "StartAddress": 86392,
    "EndAddress": 86399,
    "MaxLength": 8
  },
  {
    "Text": "Ok",
    "StartAddress": 86400,
    "EndAddress": 86407,
    "MaxLength": 8
  },
  {
    "Text": "TRUE",
    "StartAddress": 86408,
    "EndAddress": 86415,
    "MaxLength": 8
  },
  {
    "Text": "FALSE",
    "StartAddress": 86416,
    "EndAddress": 86423,
    "MaxLength": 8
  },
  {
    "Text": "You got ",
    "StartAddress": 86424,
    "EndAddress": 86439,
    "MaxLength": 16
  },
  {
    "Text": "You gave",
    "StartAddress": 86440,
    "EndAddress": 86455,
    "MaxLength": 16
  },
  {
    "Text": "You used ",
    "StartAddress": 86456,
    "EndAddress": 86471,
    "MaxLength": 16
  },
  {
    "Text": "You got\n<1>%s Monster Card%s</1>",
    "StartAddress": 86472,
    "EndAddress": 86511,
    "MaxLength": 40
  },
  {
    "Text": "Monster Card",
    "StartAddress": 86512,
    "EndAddress": 86527,
    "MaxLength": 16
  },
  {
    "Text": "You found a <1>MONSTER CARD</1>!",
    "StartAddress": 86528,
    "EndAddress": 86567,
    "MaxLength": 40
  },
  {
    "Text": "You can <1>VIEW</1> your collection,\n or <1>EQUIP</1> cards on your <1>SUBSCREEN</1>!",
    "StartAddress": 86568,
    "EndAddress": 86655,
    "MaxLength": 88
  },
  {
    "Text": "Hold to Skip",
    "StartAddress": 86656,
    "EndAddress": 86671,
    "MaxLength": 16
  },
  {
    "Text": "Press <IB action=Pause offsety=0.20/> to Skip",
    "StartAddress": 86672,
    "EndAddress": 86719,
    "MaxLength": 48
  },
  {
    "Text": "You Made A\n%s!",
    "StartAddress": 86720,
    "EndAddress": 86735,
    "MaxLength": 16
  },
  {
    "Text": "Controller disconnected. Reconnect controller, or tap Continue to switch to touch controls.",
    "StartAddress": 86736,
    "EndAddress": 86831,
    "MaxLength": 96
  },
  {
    "Text": "Controller disconnected. Reconnect controller to resume.",
    "StartAddress": 86832,
    "EndAddress": 86895,
    "MaxLength": 64
  },
  {
    "Text": "Continue",
    "StartAddress": 86896,
    "EndAddress": 86911,
    "MaxLength": 16
  },
  {
    "Text": "Special 2",
    "StartAddress": 86912,
    "EndAddress": 86927,
    "MaxLength": 16
  },
  {
    "Text": "Attack",
    "StartAddress": 86928,
    "EndAddress": 86935,
    "MaxLength": 8
  },
  {
    "Text": "Ability",
    "StartAddress": 86936,
    "EndAddress": 86943,
    "MaxLength": 8
  },
  {
    "Text": "Confirm",
    "StartAddress": 86944,
    "EndAddress": 86951,
    "MaxLength": 8
  },
  {
    "Text": "Dance",
    "StartAddress": 86952,
    "EndAddress": 86959,
    "MaxLength": 8
  },
  {
    "Text": "Special 3",
    "StartAddress": 86960,
    "EndAddress": 86975,
    "MaxLength": 16
  },
  {
    "Text": "Down",
    "StartAddress": 86976,
    "EndAddress": 86983,
    "MaxLength": 8
  },
  {
    "Text": "Magic",
    "StartAddress": 86984,
    "EndAddress": 86991,
    "MaxLength": 8
  },
  {
    "Text": "Jump",
    "StartAddress": 86992,
    "EndAddress": 86999,
    "MaxLength": 8
  },
  {
    "Text": "Left",
    "StartAddress": 87000,
    "EndAddress": 87007,
    "MaxLength": 8
  },
  {
    "Text": "Cycle Right",
    "StartAddress": 87008,
    "EndAddress": 87023,
    "MaxLength": 16
  },
  {
    "Text": "Pause",
    "StartAddress": 87024,
    "EndAddress": 87031,
    "MaxLength": 8
  },
  {
    "Text": "Cycle Left",
    "StartAddress": 87032,
    "EndAddress": 87047,
    "MaxLength": 16
  },
  {
    "Text": "Right",
    "StartAddress": 87048,
    "EndAddress": 87055,
    "MaxLength": 8
  },
  {
    "Text": "Up",
    "StartAddress": 87056,
    "EndAddress": 87063,
    "MaxLength": 8
  },
  {
    "Text": "Dash",
    "StartAddress": 87064,
    "EndAddress": 87071,
    "MaxLength": 8
  },
  {
    "Text": "Stomp",
    "StartAddress": 87072,
    "EndAddress": 87079,
    "MaxLength": 8
  },
  {
    "Text": "Subscreen",
    "StartAddress": 87080,
    "EndAddress": 87095,
    "MaxLength": 16
  },
  {
    "Text": "Loading",
    "StartAddress": 87096,
    "EndAddress": 87103,
    "MaxLength": 8
  },
  {
    "Text": "<IB action=Confirm scale=1.75/>",
    "StartAddress": 87104,
    "EndAddress": 87135,
    "MaxLength": 32
  },
  {
    "Text": "Select",
    "StartAddress": 87136,
    "EndAddress": 87143,
    "MaxLength": 8
  },
  {
    "Text": "Would you like to go to the shop now?",
    "StartAddress": 87144,
    "EndAddress": 87183,
    "MaxLength": 40
  },
  {
    "Text": "Would you like to go to the Xbox Games Store now?",
    "StartAddress": 87184,
    "EndAddress": 87239,
    "MaxLength": 56
  },
  {
    "Text": "Would you like to go to the PlayStation®Store now?",
    "StartAddress": 87240,
    "EndAddress": 87295,
    "MaxLength": 56
  },
  {
    "Text": "Would you like to go to the Nintendo eShop now?",
    "StartAddress": 87296,
    "EndAddress": 87343,
    "MaxLength": 48
  },
  {
    "Text": "New DLC installed:",
    "StartAddress": 87344,
    "EndAddress": 87367,
    "MaxLength": 24
  },
  {
    "Text": "Press <IB action=Confirm scale=1.5/>",
    "StartAddress": 87368,
    "EndAddress": 87407,
    "MaxLength": 40
  },
  {
    "Text": "Continue  <IB action=Confirm scale=0.8f/>",
    "StartAddress": 87408,
    "EndAddress": 87455,
    "MaxLength": 48
  },
  {
    "Text": "© 2020 WayForward Technologies. Shantae and the Shantae logo ™ Bozon.",
    "StartAddress": 87456,
    "EndAddress": 87535,
    "MaxLength": 80
  },
  {
    "Text": "Press  <IB action=Confirm scale=0.8f/>",
    "StartAddress": 87536,
    "EndAddress": 87575,
    "MaxLength": 40
  },
  {
    "Text": "Touch to Start",
    "StartAddress": 87576,
    "EndAddress": 87591,
    "MaxLength": 16
  },
  {
    "Text": "Are you sure you want to quit the game?",
    "StartAddress": 87592,
    "EndAddress": 87631,
    "MaxLength": 40
  },
  {
    "Text": "Start",
    "StartAddress": 87632,
    "EndAddress": 87639,
    "MaxLength": 8
  },
  {
    "Text": "Exit",
    "StartAddress": 87640,
    "EndAddress": 87647,
    "MaxLength": 8
  },
  {
    "Text": "START",
    "StartAddress": 87648,
    "EndAddress": 87655,
    "MaxLength": 8
  },
  {
    "Text": "OPTIONS",
    "StartAddress": 87656,
    "EndAddress": 87663,
    "MaxLength": 8
  },
  {
    "Text": "EXTRAS",
    "StartAddress": 87664,
    "EndAddress": 87671,
    "MaxLength": 8
  },
  {
    "Text": "QUIT",
    "StartAddress": 87672,
    "EndAddress": 87679,
    "MaxLength": 8
  },
  {
    "Text": "Which file would you like to copy?",
    "StartAddress": 87680,
    "EndAddress": 87719,
    "MaxLength": 40
  },
  {
    "Text": "Copy file to where?",
    "StartAddress": 87720,
    "EndAddress": 87743,
    "MaxLength": 24
  },
  {
    "Text": "Which file would you like to erase?",
    "StartAddress": 87744,
    "EndAddress": 87783,
    "MaxLength": 40
  },
  {
    "Text": "Copy",
    "StartAddress": 87784,
    "EndAddress": 87791,
    "MaxLength": 8
  },
  {
    "Text": "Erase",
    "StartAddress": 87792,
    "EndAddress": 87799,
    "MaxLength": 8
  },
  {
    "Text": "Options",
    "StartAddress": 87800,
    "EndAddress": 87807,
    "MaxLength": 8
  },
  {
    "Text": "Extras",
    "StartAddress": 87808,
    "EndAddress": 87815,
    "MaxLength": 8
  },
  {
    "Text": "New Game",
    "StartAddress": 87816,
    "EndAddress": 87831,
    "MaxLength": 16
  },
  {
    "Text": "Are you sure you want to erase this file?",
    "StartAddress": 87832,
    "EndAddress": 87879,
    "MaxLength": 48
  },
  {
    "Text": "Are you sure you want to copy this file?",
    "StartAddress": 87880,
    "EndAddress": 87927,
    "MaxLength": 48
  },
  {
    "Text": "File %d",
    "StartAddress": 87928,
    "EndAddress": 87935,
    "MaxLength": 8
  },
  {
    "Text": "Cannot connect to the cloud server\nUsing Local Save\nBeware of override",
    "StartAddress": 87936,
    "EndAddress": 88007,
    "MaxLength": 72
  },
  {
    "Text": "00 : 00",
    "StartAddress": 88008,
    "EndAddress": 88015,
    "MaxLength": 8
  },
  {
    "Text": "Mode Select",
    "StartAddress": 88016,
    "EndAddress": 88031,
    "MaxLength": 16
  },
  {
    "Text": "Original",
    "StartAddress": 88032,
    "EndAddress": 88047,
    "MaxLength": 16
  },
  {
    "Text": "Play the game in its original mode!",
    "StartAddress": 88048,
    "EndAddress": 88087,
    "MaxLength": 40
  },
  {
    "Text": "New Game +",
    "StartAddress": 88088,
    "EndAddress": 88103,
    "MaxLength": 16
  },
  {
    "Text": "More magic, but less defense!",
    "StartAddress": 88104,
    "EndAddress": 88135,
    "MaxLength": 32
  },
  {
    "Text": "Part One",
    "StartAddress": 88136,
    "EndAddress": 88151,
    "MaxLength": 16
  },
  {
    "Text": "Welcome!",
    "StartAddress": 88152,
    "EndAddress": 88167,
    "MaxLength": 16
  },
  {
    "Text": "You are about to enjoy Shantae and the Seven Sirens PART 1.\n\nAt the conclusion of PART 1, your game progress will be saved so it can be\nloaded into PART 2, which will arrive via a future free update.\n\nWe hope you will enjoy Shantae and the Seven Sirens!",
    "StartAddress": 88168,
    "EndAddress": 88423,
    "MaxLength": 256
  },
  {
    "Text": "Part Two",
    "StartAddress": 88424,
    "EndAddress": 88439,
    "MaxLength": 16
  },
  {
    "Text": "Welcome back!",
    "StartAddress": 88440,
    "EndAddress": 88455,
    "MaxLength": 16
  },
  {
    "Text": "\nYour game progress from PART 1 has been loaded!\n\nGet ready for the exciting conclusion to Shantae and the Seven Sirens!",
    "StartAddress": 88456,
    "EndAddress": 88583,
    "MaxLength": 128
  },
  {
    "Text": "End of Part One",
    "StartAddress": 88584,
    "EndAddress": 88599,
    "MaxLength": 16
  },
  {
    "Text": "Thank you for playing PART 1 of Shantae and the Seven Sirens!\n\nYour adventure has been saved. You may continue to explore the\ngame world using the current Save File!\n\nAny new items you collect will be carried over when the\nfree update containing PART 2 arrives. Enjoy!",
    "StartAddress": 88600,
    "EndAddress": 88871,
    "MaxLength": 272
  },
  {
    "Text": "Movie Viewer",
    "StartAddress": 88872,
    "EndAddress": 88887,
    "MaxLength": 16
  },
  {
    "Text": "???",
    "StartAddress": 88904,
    "EndAddress": 88911,
    "MaxLength": 8
  },
  {
    "Text": "100% Items!",
    "StartAddress": 88912,
    "EndAddress": 88927,
    "MaxLength": 16
  },
  {
    "Text": "Complete the game with 100% items at any speed.",
    "StartAddress": 88928,
    "EndAddress": 88975,
    "MaxLength": 48
  },
  {
    "Text": "Winner!",
    "StartAddress": 88976,
    "EndAddress": 88983,
    "MaxLength": 8
  },
  {
    "Text": "Complete the game with any % items at any speed.",
    "StartAddress": 88984,
    "EndAddress": 89039,
    "MaxLength": 56
  },
  {
    "Text": "100% Items, Fast!",
    "StartAddress": 89040,
    "EndAddress": 89063,
    "MaxLength": 24
  },
  {
    "Text": "Complete the game with 100% items at high speed.",
    "StartAddress": 89064,
    "EndAddress": 89119,
    "MaxLength": 56
  },
  {
    "Text": "Top Speed!",
    "StartAddress": 89120,
    "EndAddress": 89135,
    "MaxLength": 16
  },
  {
    "Text": "Complete the game at any % at extremely high speed.",
    "StartAddress": 89136,
    "EndAddress": 89191,
    "MaxLength": 56
  },
  {
    "Text": "Extras",
    "StartAddress": 89192,
    "EndAddress": 89199,
    "MaxLength": 8
  },
  {
    "Text": "Win Screens",
    "StartAddress": 89200,
    "EndAddress": 89215,
    "MaxLength": 16
  },
  {
    "Text": "Movie Viewer",
    "StartAddress": 89216,
    "EndAddress": 89231,
    "MaxLength": 16
  },
  {
    "Text": "Credits",
    "StartAddress": 89232,
    "EndAddress": 89239,
    "MaxLength": 8
  },
  {
    "Text": "Achievements",
    "StartAddress": 89240,
    "EndAddress": 89255,
    "MaxLength": 16
  },
  {
    "Text": "File",
    "StartAddress": 89256,
    "EndAddress": 89263,
    "MaxLength": 8
  },
  {
    "Text": "Continue",
    "StartAddress": 89264,
    "EndAddress": 89279,
    "MaxLength": 16
  },
  {
    "Text": "New Game",
    "StartAddress": 89280,
    "EndAddress": 89319,
    "MaxLength": 40
  },
  {
    "Text": "OPTIONS",
    "StartAddress": 89320,
    "EndAddress": 89327,
    "MaxLength": 8
  },
  {
    "Text": "SFX",
    "StartAddress": 89328,
    "EndAddress": 89335,
    "MaxLength": 8
  },
  {
    "Text": "Music",
    "StartAddress": 89336,
    "EndAddress": 89343,
    "MaxLength": 8
  },
  {
    "Text": "Volume",
    "StartAddress": 89344,
    "EndAddress": 89351,
    "MaxLength": 8
  },
  {
    "Text": "Resolution",
    "StartAddress": 89352,
    "EndAddress": 89367,
    "MaxLength": 16
  },
  {
    "Text": "Screen Mode",
    "StartAddress": 89368,
    "EndAddress": 89383,
    "MaxLength": 16
  },
  {
    "Text": "Windowed",
    "StartAddress": 89384,
    "EndAddress": 89399,
    "MaxLength": 16
  },
  {
    "Text": "Fullscreen",
    "StartAddress": 89400,
    "EndAddress": 89415,
    "MaxLength": 16
  },
  {
    "Text": "Controls",
    "StartAddress": 89416,
    "EndAddress": 89431,
    "MaxLength": 16
  },
  {
    "Text": "Controller Configuration",
    "StartAddress": 89432,
    "EndAddress": 89463,
    "MaxLength": 32
  },
  {
    "Text": "Apply",
    "StartAddress": 89464,
    "EndAddress": 89471,
    "MaxLength": 8
  },
  {
    "Text": "Cancel",
    "StartAddress": 89472,
    "EndAddress": 89479,
    "MaxLength": 8
  },
  {
    "Text": "Resolution saved. You must restart the game for the settings to take effect. Restart now?",
    "StartAddress": 89480,
    "EndAddress": 89575,
    "MaxLength": 96
  },
  {
    "Text": "Profile",
    "StartAddress": 89576,
    "EndAddress": 89583,
    "MaxLength": 8
  },
  {
    "Text": "Help",
    "StartAddress": 89584,
    "EndAddress": 89591,
    "MaxLength": 8
  },
  {
    "Text": "Anti-Aliasing",
    "StartAddress": 89592,
    "EndAddress": 89607,
    "MaxLength": 16
  },
  {
    "Text": "On",
    "StartAddress": 89608,
    "EndAddress": 89615,
    "MaxLength": 8
  },
  {
    "Text": "Off",
    "StartAddress": 89616,
    "EndAddress": 89623,
    "MaxLength": 8
  },
  {
    "Text": "Dynamic",
    "StartAddress": 89624,
    "EndAddress": 89631,
    "MaxLength": 8
  },
  {
    "Text": "Brightness",
    "StartAddress": 89632,
    "EndAddress": 89647,
    "MaxLength": 16
  },
  {
    "Text": "Vibration",
    "StartAddress": 89648,
    "EndAddress": 89663,
    "MaxLength": 16
  },
  {
    "Text": "On",
    "StartAddress": 89664,
    "EndAddress": 89671,
    "MaxLength": 8
  },
  {
    "Text": "Off",
    "StartAddress": 89672,
    "EndAddress": 89679,
    "MaxLength": 8
  },
  {
    "Text": "Language",
    "StartAddress": 89680,
    "EndAddress": 89695,
    "MaxLength": 16
  },
  {
    "Text": "Default",
    "StartAddress": 89696,
    "EndAddress": 89703,
    "MaxLength": 8
  },
  {
    "Text": "Credits",
    "StartAddress": 89704,
    "EndAddress": 89711,
    "MaxLength": 8
  },
  {
    "Text": "English",
    "StartAddress": 89712,
    "EndAddress": 89719,
    "MaxLength": 8
  },
  {
    "Text": "French",
    "StartAddress": 89720,
    "EndAddress": 89727,
    "MaxLength": 8
  },
  {
    "Text": "Italian",
    "StartAddress": 89728,
    "EndAddress": 89735,
    "MaxLength": 8
  },
  {
    "Text": "German",
    "StartAddress": 89736,
    "EndAddress": 89743,
    "MaxLength": 8
  },
  {
    "Text": "Spanish",
    "StartAddress": 89744,
    "EndAddress": 89751,
    "MaxLength": 8
  },
  {
    "Text": "Portuguese",
    "StartAddress": 89752,
    "EndAddress": 89767,
    "MaxLength": 16
  },
  {
    "Text": "Dutch",
    "StartAddress": 89768,
    "EndAddress": 89775,
    "MaxLength": 8
  },
  {
    "Text": "Russian",
    "StartAddress": 89776,
    "EndAddress": 89783,
    "MaxLength": 8
  },
  {
    "Text": "Turkish",
    "StartAddress": 89784,
    "EndAddress": 89791,
    "MaxLength": 8
  },
  {
    "Text": "Arabic",
    "StartAddress": 89792,
    "EndAddress": 89799,
    "MaxLength": 8
  },
  {
    "Text": "Japanese",
    "StartAddress": 89800,
    "EndAddress": 89815,
    "MaxLength": 16
  },
  {
    "Text": "Korean",
    "StartAddress": 89816,
    "EndAddress": 89823,
    "MaxLength": 8
  },
  {
    "Text": "Chinese Simple",
    "StartAddress": 89824,
    "EndAddress": 89839,
    "MaxLength": 16
  },
  {
    "Text": "Chinese Traditional",
    "StartAddress": 89840,
    "EndAddress": 89863,
    "MaxLength": 24
  },
  {
    "Text": "Level of Detail",
    "StartAddress": 89864,
    "EndAddress": 89879,
    "MaxLength": 16
  },
  {
    "Text": "High",
    "StartAddress": 89880,
    "EndAddress": 89887,
    "MaxLength": 8
  },
  {
    "Text": "Mid",
    "StartAddress": 89888,
    "EndAddress": 89895,
    "MaxLength": 8
  },
  {
    "Text": "Low",
    "StartAddress": 89896,
    "EndAddress": 89903,
    "MaxLength": 8
  },
  {
    "Text": "Touch Handedness",
    "StartAddress": 89904,
    "EndAddress": 89927,
    "MaxLength": 24
  },
  {
    "Text": "Left-Handed",
    "StartAddress": 89928,
    "EndAddress": 89943,
    "MaxLength": 16
  },
  {
    "Text": "Right-Handed",
    "StartAddress": 89944,
    "EndAddress": 89959,
    "MaxLength": 16
  },
  {
    "Text": "Touch Configuration",
    "StartAddress": 89960,
    "EndAddress": 89983,
    "MaxLength": 24
  },
  {
    "Text": "Movie Subtitles",
    "StartAddress": 89984,
    "EndAddress": 89999,
    "MaxLength": 16
  },
  {
    "Text": "Configure",
    "StartAddress": 90000,
    "EndAddress": 90015,
    "MaxLength": 16
  },
  {
    "Text": "Cancel",
    "StartAddress": 90016,
    "EndAddress": 90023,
    "MaxLength": 8
  },
  {
    "Text": "Defaults",
    "StartAddress": 90024,
    "EndAddress": 90039,
    "MaxLength": 16
  },
  {
    "Text": "Apply",
    "StartAddress": 90040,
    "EndAddress": 90047,
    "MaxLength": 8
  },
  {
    "Text": "Keyboard",
    "StartAddress": 90048,
    "EndAddress": 90063,
    "MaxLength": 16
  },
  {
    "Text": "Gamepad",
    "StartAddress": 90064,
    "EndAddress": 90071,
    "MaxLength": 8
  },
  {
    "Text": "Press key to change to",
    "StartAddress": 90072,
    "EndAddress": 90095,
    "MaxLength": 24
  },
  {
    "Text": "Set Bindings For:",
    "StartAddress": 90096,
    "EndAddress": 90119,
    "MaxLength": 24
  },
  {
    "Text": "No Binding!",
    "StartAddress": 90120,
    "EndAddress": 90135,
    "MaxLength": 16
  },
  {
    "Text": "Are you sure you want lose changes made to touch controls?",
    "StartAddress": 90136,
    "EndAddress": 90199,
    "MaxLength": 64
  },
  {
    "Text": "Scale:",
    "StartAddress": 90200,
    "EndAddress": 90207,
    "MaxLength": 8
  },
  {
    "Text": "Opacity:",
    "StartAddress": 90208,
    "EndAddress": 90223,
    "MaxLength": 16
  },
  {
    "Text": "Tap a button to resize, click and drag the button to adjust the positioning.",
    "StartAddress": 90224,
    "EndAddress": 90303,
    "MaxLength": 80
  },
  {
    "Text": "Would you like to Save your Progress?",
    "StartAddress": 90304,
    "EndAddress": 90343,
    "MaxLength": 40
  },
  {
    "Text": "Saving...",
    "StartAddress": 90344,
    "EndAddress": 90359,
    "MaxLength": 16
  },
  {
    "Text": "Save complete!",
    "StartAddress": 90360,
    "EndAddress": 90375,
    "MaxLength": 16
  },
  {
    "Text": "Save failed.",
    "StartAddress": 90376,
    "EndAddress": 90391,
    "MaxLength": 16
  },
  {
    "Text": "Game Paused",
    "StartAddress": 90392,
    "EndAddress": 90407,
    "MaxLength": 16
  },
  {
    "Text": "Resume",
    "StartAddress": 90408,
    "EndAddress": 90415,
    "MaxLength": 8
  },
  {
    "Text": "Quit",
    "StartAddress": 90416,
    "EndAddress": 90423,
    "MaxLength": 8
  },
  {
    "Text": "Options",
    "StartAddress": 90424,
    "EndAddress": 90431,
    "MaxLength": 8
  },
  {
    "Text": "Stage Select",
    "StartAddress": 90432,
    "EndAddress": 90447,
    "MaxLength": 16
  },
  {
    "Text": "Skip Tutorial",
    "StartAddress": 90448,
    "EndAddress": 90463,
    "MaxLength": 16
  },
  {
    "Text": "Any unsaved progress will be lost.\n Are you sure you want to quit?",
    "StartAddress": 90464,
    "EndAddress": 90535,
    "MaxLength": 72
  },
  {
    "Text": "Skip the remaining tutorials?",
    "StartAddress": 90536,
    "EndAddress": 90567,
    "MaxLength": 32
  },
  {
    "Text": "Map",
    "StartAddress": 90568,
    "EndAddress": 90575,
    "MaxLength": 8
  },
  {
    "Text": "Cards",
    "StartAddress": 90576,
    "EndAddress": 90583,
    "MaxLength": 8
  },
  {
    "Text": "Press <IB action=PreviousItem scale=0.5f/> or <IB action=NextItem scale=0.5f/> to switch panels",
    "StartAddress": 90584,
    "EndAddress": 90679,
    "MaxLength": 96
  },
  {
    "Text": "Options",
    "StartAddress": 90680,
    "EndAddress": 90687,
    "MaxLength": 8
  },
  {
    "Text": "Quit",
    "StartAddress": 90688,
    "EndAddress": 90695,
    "MaxLength": 8
  },
  {
    "Text": "Relics",
    "StartAddress": 90696,
    "EndAddress": 90703,
    "MaxLength": 8
  },
  {
    "Text": "Dances",
    "StartAddress": 90704,
    "EndAddress": 90711,
    "MaxLength": 8
  },
  {
    "Text": "Inventory",
    "StartAddress": 90712,
    "EndAddress": 90727,
    "MaxLength": 16
  },
  {
    "Text": "Key Items",
    "StartAddress": 90728,
    "EndAddress": 90743,
    "MaxLength": 16
  },
  {
    "Text": "Fusions",
    "StartAddress": 90744,
    "EndAddress": 90751,
    "MaxLength": 8
  },
  {
    "Text": "Cards",
    "StartAddress": 90752,
    "EndAddress": 90759,
    "MaxLength": 8
  },
  {
    "Text": "Items",
    "StartAddress": 90760,
    "EndAddress": 90767,
    "MaxLength": 8
  },
  {
    "Text": "Map",
    "StartAddress": 90768,
    "EndAddress": 90775,
    "MaxLength": 8
  },
  {
    "Text": "System",
    "StartAddress": 90776,
    "EndAddress": 90783,
    "MaxLength": 8
  },
  {
    "Text": "Use",
    "StartAddress": 90784,
    "EndAddress": 90791,
    "MaxLength": 8
  },
  {
    "Text": "Cancel",
    "StartAddress": 90792,
    "EndAddress": 90799,
    "MaxLength": 8
  },
  {
    "Text": "<IB action=Dance/> Area Map",
    "StartAddress": 90800,
    "EndAddress": 90831,
    "MaxLength": 32
  },
  {
    "Text": "<IB action=Dance/> World Map",
    "StartAddress": 90832,
    "EndAddress": 90863,
    "MaxLength": 32
  },
  {
    "Text": "<IB action=Attack/> Zoom In",
    "StartAddress": 90864,
    "EndAddress": 90895,
    "MaxLength": 32
  },
  {
    "Text": "<IB action=Attack/> Zoom Out",
    "StartAddress": 90896,
    "EndAddress": 90927,
    "MaxLength": 32
  },
  {
    "Text": "World Map",
    "StartAddress": 90928,
    "EndAddress": 90943,
    "MaxLength": 16
  },
  {
    "Text": "Half-Genie",
    "StartAddress": 90944,
    "EndAddress": 90959,
    "MaxLength": 16
  },
  {
    "Text": "Save",
    "StartAddress": 90960,
    "EndAddress": 90967,
    "MaxLength": 8
  },
  {
    "Text": "Warp Room",
    "StartAddress": 90968,
    "EndAddress": 90983,
    "MaxLength": 16
  },
  {
    "Text": "Labyrinth",
    "StartAddress": 90984,
    "EndAddress": 90999,
    "MaxLength": 16
  },
  {
    "Text": "Boss",
    "StartAddress": 91000,
    "EndAddress": 91007,
    "MaxLength": 8
  },
  {
    "Text": "Town",
    "StartAddress": 91008,
    "EndAddress": 91015,
    "MaxLength": 8
  },
  {
    "Text": "Lab Entrance",
    "StartAddress": 91016,
    "EndAddress": 91031,
    "MaxLength": 16
  },
  {
    "Text": "Monster Cards",
    "StartAddress": 91032,
    "EndAddress": 91047,
    "MaxLength": 16
  },
  {
    "Text": "Back",
    "StartAddress": 91048,
    "EndAddress": 91055,
    "MaxLength": 8
  },
  {
    "Text": "Item Shop",
    "StartAddress": 91056,
    "EndAddress": 91071,
    "MaxLength": 16
  },
  {
    "Text": "Yes",
    "StartAddress": 91072,
    "EndAddress": 91079,
    "MaxLength": 8
  },
  {
    "Text": "No",
    "StartAddress": 91080,
    "EndAddress": 91087,
    "MaxLength": 8
  },
  {
    "Text": "SOLD OUT!",
    "StartAddress": 91088,
    "EndAddress": 91103,
    "MaxLength": 16
  },
  {
    "Text": "Sorry, not enough gems!",
    "StartAddress": 91104,
    "EndAddress": 91127,
    "MaxLength": 24
  },
  {
    "Text": "Purchase for <I anim=ui_game:hud.anb seq=gem scale=0.75f offsety=0.3f offsetx=0.2f width=0.5f/>%03d ?",
    "StartAddress": 91128,
    "EndAddress": 91231,
    "MaxLength": 104
  },
  {
    "Text": "Exit the shop!",
    "StartAddress": 91232,
    "EndAddress": 91247,
    "MaxLength": 16
  },
  {
    "Text": "Game Over!",
    "StartAddress": 91248,
    "EndAddress": 91263,
    "MaxLength": 16
  },
  {
    "Text": "Continue",
    "StartAddress": 91264,
    "EndAddress": 91279,
    "MaxLength": 16
  },
  {
    "Text": "Quit",
    "StartAddress": 91280,
    "EndAddress": 91287,
    "MaxLength": 8
  },
  {
    "Text": "Play Time",
    "StartAddress": 91288,
    "EndAddress": 91303,
    "MaxLength": 16
  },
  {
    "Text": "Item Collection",
    "StartAddress": 91304,
    "EndAddress": 91319,
    "MaxLength": 16
  },
  {
    "Text": "Press",
    "StartAddress": 91320,
    "EndAddress": 91327,
    "MaxLength": 8
  },
  {
    "Text": "Bonus image - Game Clear, Fastest time!",
    "StartAddress": 91328,
    "EndAddress": 91367,
    "MaxLength": 40
  },
  {
    "Text": "Bonus image - Fastest time, 100%!",
    "StartAddress": 91368,
    "EndAddress": 91407,
    "MaxLength": 40
  },
  {
    "Text": "Bonus image - 100% clear!",
    "StartAddress": 91408,
    "EndAddress": 91439,
    "MaxLength": 32
  },
  {
    "Text": "Bonus image - Game Clear!",
    "StartAddress": 91440,
    "EndAddress": 91471,
    "MaxLength": 32
  },
  {
    "Text": "Play",
    "StartAddress": 91472,
    "EndAddress": 91479,
    "MaxLength": 8
  },
  {
    "Text": "Rules",
    "StartAddress": 91480,
    "EndAddress": 91487,
    "MaxLength": 8
  },
  {
    "Text": "1: 10 Gems",
    "StartAddress": 91488,
    "EndAddress": 91503,
    "MaxLength": 16
  },
  {
    "Text": "2: 18 Gems",
    "StartAddress": 91504,
    "EndAddress": 91519,
    "MaxLength": 16
  },
  {
    "Text": "3: 25 Gems",
    "StartAddress": 91520,
    "EndAddress": 91535,
    "MaxLength": 16
  },
  {
    "Text": "ALL CLEAR! YOU GET %s BONUS GEMS",
    "StartAddress": 91536,
    "EndAddress": 91575,
    "MaxLength": 40
  },
  {
    "Text": "You don't have enough gems to continue playing!",
    "StartAddress": 91576,
    "EndAddress": 91623,
    "MaxLength": 48
  },
  {
    "Text": "Total Gems",
    "StartAddress": 91624,
    "EndAddress": 91639,
    "MaxLength": 16
  },
  {
    "Text": "Shots",
    "StartAddress": 91640,
    "EndAddress": 91647,
    "MaxLength": 8
  },
  {
    "Text": "GO!",
    "StartAddress": 91648,
    "EndAddress": 91655,
    "MaxLength": 8
  },
  {
    "Text": "How To Play",
    "StartAddress": 91656,
    "EndAddress": 91671,
    "MaxLength": 16
  },
  {
    "Text": "Got It!",
    "StartAddress": 91672,
    "EndAddress": 91679,
    "MaxLength": 8
  },
  {
    "Text": "MOVE",
    "StartAddress": 91680,
    "EndAddress": 91687,
    "MaxLength": 8
  },
  {
    "Text": "JUMP",
    "StartAddress": 91688,
    "EndAddress": 91695,
    "MaxLength": 8
  },
  {
    "Text": "ATTACK",
    "StartAddress": 91696,
    "EndAddress": 91703,
    "MaxLength": 8
  },
  {
    "Text": "USE",
    "StartAddress": 91704,
    "EndAddress": 91711,
    "MaxLength": 8
  },
  {
    "Text": "CYCLE",
    "StartAddress": 91712,
    "EndAddress": 91719,
    "MaxLength": 8
  },
  {
    "Text": "DANCE",
    "StartAddress": 91720,
    "EndAddress": 91727,
    "MaxLength": 8
  },
  {
    "Text": "MENU",
    "StartAddress": 91728,
    "EndAddress": 91735,
    "MaxLength": 8
  },
  {
    "Text": "You got the PLAYER'S GUIDE!",
    "StartAddress": 91736,
    "EndAddress": 91767,
    "MaxLength": 32
  },
  {
    "Text": "If you ever want a refresher on how to play, tap this item in your inventory.",
    "StartAddress": 91768,
    "EndAddress": 91847,
    "MaxLength": 80
  },
  {
    "Text": "Default controls shown. Controls may be customized in the options screen.",
    "StartAddress": 91848,
    "EndAddress": 91927,
    "MaxLength": 80
  },
  {
    "Text": "Your save data on the cloud and on your device are different.",
    "StartAddress": 91928,
    "EndAddress": 91991,
    "MaxLength": 64
  },
  {
    "Text": "Please choose one to keep.",
    "StartAddress": 91992,
    "EndAddress": 92023,
    "MaxLength": 32
  },
  {
    "Text": "The other will be discarded.",
    "StartAddress": 92024,
    "EndAddress": 92055,
    "MaxLength": 32
  },
  {
    "Text": "Your GameCenter ID: %s",
    "StartAddress": 92056,
    "EndAddress": 92079,
    "MaxLength": 24
  },
  {
    "Text": "Device:",
    "StartAddress": 92080,
    "EndAddress": 92087,
    "MaxLength": 8
  },
  {
    "Text": "Device: %s\nLast save:\n%s",
    "StartAddress": 92088,
    "EndAddress": 92119,
    "MaxLength": 32
  },
  {
    "Text": "Last save:",
    "StartAddress": 92120,
    "EndAddress": 92135,
    "MaxLength": 16
  },
  {
    "Text": "Device: %s\nLast save:\n%s",
    "StartAddress": 92136,
    "EndAddress": 92167,
    "MaxLength": 32
  },
  {
    "Text": "Local",
    "StartAddress": 92168,
    "EndAddress": 92175,
    "MaxLength": 8
  },
  {
    "Text": "iCloud",
    "StartAddress": 92176,
    "EndAddress": 92183,
    "MaxLength": 8
  },
  {
    "Text": "KEEP",
    "StartAddress": 92184,
    "EndAddress": 92191,
    "MaxLength": 8
  },
  {
    "Text": "Unknown",
    "StartAddress": 92192,
    "EndAddress": 92199,
    "MaxLength": 8
  },
  {
    "Text": "Warning: Choosing one save will delete the other",
    "StartAddress": 92200,
    "EndAddress": 92255,
    "MaxLength": 56
  },
  {
    "Text": "Warning: Select Local to override both. Select Cloud to Load and go back to Title.",
    "StartAddress": 92256,
    "EndAddress": 92343,
    "MaxLength": 88
  },
  {
    "Text": "The Half-Genies mysteriously disappeared...",
    "StartAddress": 92344,
    "EndAddress": 92391,
    "MaxLength": 48
  },
  {
    "Text": "...And just like that, the festival was over.",
    "StartAddress": 92392,
    "EndAddress": 92439,
    "MaxLength": 48
  },
  {
    "Text": "The next morning...",
    "StartAddress": 92440,
    "EndAddress": 92463,
    "MaxLength": 24
  },
  {
    "Text": "...The day was saved.",
    "StartAddress": 92464,
    "EndAddress": 92487,
    "MaxLength": 24
  },
  {
    "Text": "Before long, it was time to return home...",
    "StartAddress": 92488,
    "EndAddress": 92535,
    "MaxLength": 48
  },
  {
    "Text": "Character Select",
    "StartAddress": 92536,
    "EndAddress": 92559,
    "MaxLength": 24
  },
  {
    "Text": "File Select",
    "StartAddress": 92560,
    "EndAddress": 92575,
    "MaxLength": 16
  },
  {
    "Text": "Options",
    "StartAddress": 92576,
    "EndAddress": 92583,
    "MaxLength": 8
  },
  {
    "Text": "World Clear!",
    "StartAddress": 92584,
    "EndAddress": 92599,
    "MaxLength": 16
  },
  {
    "Text": "Ready?",
    "StartAddress": 92600,
    "EndAddress": 92607,
    "MaxLength": 8
  },
  {
    "Text": "Game Over",
    "StartAddress": 92608,
    "EndAddress": 92623,
    "MaxLength": 16
  },
  {
    "Text": "50 Gems",
    "StartAddress": 92624,
    "EndAddress": 92631,
    "MaxLength": 8
  },
  {
    "Text": "100 Gems",
    "StartAddress": 92632,
    "EndAddress": 92647,
    "MaxLength": 16
  },
  {
    "Text": "Attract",
    "StartAddress": 92648,
    "EndAddress": 92655,
    "MaxLength": 8
  },
  {
    "Text": "Super Attract",
    "StartAddress": 92656,
    "EndAddress": 92671,
    "MaxLength": 16
  },
  {
    "Text": "Max Attract",
    "StartAddress": 92672,
    "EndAddress": 92687,
    "MaxLength": 16
  },
  {
    "Text": "Auto Potion",
    "StartAddress": 92688,
    "EndAddress": 92703,
    "MaxLength": 16
  },
  {
    "Text": "Backdash",
    "StartAddress": 92704,
    "EndAddress": 92719,
    "MaxLength": 16
  },
  {
    "Text": "Smooth Barnacle",
    "StartAddress": 92720,
    "EndAddress": 92735,
    "MaxLength": 16
  },
  {
    "Text": "Barnacles",
    "StartAddress": 92736,
    "EndAddress": 92751,
    "MaxLength": 16
  },
  {
    "Text": "Lumpy Barnacle",
    "StartAddress": 92752,
    "EndAddress": 92767,
    "MaxLength": 16
  },
  {
    "Text": "Boss Key",
    "StartAddress": 92768,
    "EndAddress": 92783,
    "MaxLength": 16
  },
  {
    "Text": "Bran-Son Doll",
    "StartAddress": 92784,
    "EndAddress": 92799,
    "MaxLength": 16
  },
  {
    "Text": "Canned Tuna",
    "StartAddress": 92800,
    "EndAddress": 92815,
    "MaxLength": 16
  },
  {
    "Text": "Checklist",
    "StartAddress": 92816,
    "EndAddress": 92831,
    "MaxLength": 16
  },
  {
    "Text": "Codebook",
    "StartAddress": 92832,
    "EndAddress": 92847,
    "MaxLength": 16
  },
  {
    "Text": "Completed Checklist",
    "StartAddress": 92848,
    "EndAddress": 92871,
    "MaxLength": 24
  },
  {
    "Text": "Metronome",
    "StartAddress": 92872,
    "EndAddress": 92887,
    "MaxLength": 16
  },
  {
    "Text": "Dog Collar",
    "StartAddress": 92888,
    "EndAddress": 92903,
    "MaxLength": 16
  },
  {
    "Text": "Gastro Drill ",
    "StartAddress": 92904,
    "EndAddress": 92919,
    "MaxLength": 16
  },
  {
    "Text": "Bonker Tortoise",
    "StartAddress": 92920,
    "EndAddress": 92935,
    "MaxLength": 16
  },
  {
    "Text": "Friend",
    "StartAddress": 92936,
    "EndAddress": 92943,
    "MaxLength": 8
  },
  {
    "Text": "Sea Frog",
    "StartAddress": 92944,
    "EndAddress": 92959,
    "MaxLength": 16
  },
  {
    "Text": "Fused Bracelet",
    "StartAddress": 92960,
    "EndAddress": 92975,
    "MaxLength": 16
  },
  {
    "Text": "Nugget",
    "StartAddress": 92976,
    "EndAddress": 92983,
    "MaxLength": 8
  },
  {
    "Text": "Nuggets",
    "StartAddress": 92984,
    "EndAddress": 92991,
    "MaxLength": 8
  },
  {
    "Text": "Drool-Stained Doll",
    "StartAddress": 92992,
    "EndAddress": 93015,
    "MaxLength": 24
  },
  {
    "Text": "Scary Doll",
    "StartAddress": 93016,
    "EndAddress": 93031,
    "MaxLength": 16
  },
  {
    "Text": "Golden Crab",
    "StartAddress": 93032,
    "EndAddress": 93047,
    "MaxLength": 16
  },
  {
    "Text": "Handle",
    "StartAddress": 93048,
    "EndAddress": 93055,
    "MaxLength": 8
  },
  {
    "Text": "Jet Octo",
    "StartAddress": 93056,
    "EndAddress": 93071,
    "MaxLength": 16
  },
  {
    "Text": "Health Potion",
    "StartAddress": 93072,
    "EndAddress": 93087,
    "MaxLength": 16
  },
  {
    "Text": "Heart Holder",
    "StartAddress": 93088,
    "EndAddress": 93103,
    "MaxLength": 16
  },
  {
    "Text": "Heart Squid",
    "StartAddress": 93104,
    "EndAddress": 93119,
    "MaxLength": 16
  },
  {
    "Text": "How To Play",
    "StartAddress": 93120,
    "EndAddress": 93135,
    "MaxLength": 16
  },
  {
    "Text": "HP Saver",
    "StartAddress": 93136,
    "EndAddress": 93151,
    "MaxLength": 16
  },
  {
    "Text": "Key",
    "StartAddress": 93152,
    "EndAddress": 93159,
    "MaxLength": 8
  },
  {
    "Text": "Left Bracelet",
    "StartAddress": 93160,
    "EndAddress": 93175,
    "MaxLength": 16
  },
  {
    "Text": "Bracelets",
    "StartAddress": 93176,
    "EndAddress": 93191,
    "MaxLength": 16
  },
  {
    "Text": "Fusion Stone",
    "StartAddress": 93192,
    "EndAddress": 93207,
    "MaxLength": 16
  },
  {
    "Text": "Magic Potion",
    "StartAddress": 93208,
    "EndAddress": 93223,
    "MaxLength": 16
  },
  {
    "Text": "Manly Doll",
    "StartAddress": 93224,
    "EndAddress": 93239,
    "MaxLength": 16
  },
  {
    "Text": "Map",
    "StartAddress": 93240,
    "EndAddress": 93247,
    "MaxLength": 8
  },
  {
    "Text": "Lucky Amulet",
    "StartAddress": 93248,
    "EndAddress": 93263,
    "MaxLength": 16
  },
  {
    "Text": "Mermaid Shell",
    "StartAddress": 93264,
    "EndAddress": 93279,
    "MaxLength": 16
  },
  {
    "Text": "Mermaid Shells",
    "StartAddress": 93280,
    "EndAddress": 93295,
    "MaxLength": 16
  },
  {
    "Text": "Dash Newt",
    "StartAddress": 93296,
    "EndAddress": 93311,
    "MaxLength": 16
  },
  {
    "Text": "MP Saver",
    "StartAddress": 93312,
    "EndAddress": 93327,
    "MaxLength": 16
  },
  {
    "Text": "Dagron Ball",
    "StartAddress": 93328,
    "EndAddress": 93343,
    "MaxLength": 16
  },
  {
    "Text": "Dagron Balls",
    "StartAddress": 93344,
    "EndAddress": 93359,
    "MaxLength": 16
  },
  {
    "Text": "Orange",
    "StartAddress": 93360,
    "EndAddress": 93367,
    "MaxLength": 8
  },
  {
    "Text": "Ore",
    "StartAddress": 93368,
    "EndAddress": 93375,
    "MaxLength": 8
  },
  {
    "Text": "Poke Bowl",
    "StartAddress": 93376,
    "EndAddress": 93391,
    "MaxLength": 16
  },
  {
    "Text": "Shampoo",
    "StartAddress": 93392,
    "EndAddress": 93399,
    "MaxLength": 8
  },
  {
    "Text": "Super Shampoo",
    "StartAddress": 93400,
    "EndAddress": 93415,
    "MaxLength": 16
  },
  {
    "Text": "Mega Shampoo",
    "StartAddress": 93416,
    "EndAddress": 93431,
    "MaxLength": 16
  },
  {
    "Text": "Pulled Pork Sandwich",
    "StartAddress": 93432,
    "EndAddress": 93455,
    "MaxLength": 24
  },
  {
    "Text": "Nuts and Bolts",
    "StartAddress": 93456,
    "EndAddress": 93471,
    "MaxLength": 16
  },
  {
    "Text": "Right Bracelet",
    "StartAddress": 93472,
    "EndAddress": 93487,
    "MaxLength": 16
  },
  {
    "Text": "Roast",
    "StartAddress": 93488,
    "EndAddress": 93495,
    "MaxLength": 8
  },
  {
    "Text": "Roasted Pineapple",
    "StartAddress": 93496,
    "EndAddress": 93519,
    "MaxLength": 24
  },
  {
    "Text": "Useless Object",
    "StartAddress": 93520,
    "EndAddress": 93535,
    "MaxLength": 16
  },
  {
    "Text": "Salmon",
    "StartAddress": 93536,
    "EndAddress": 93543,
    "MaxLength": 8
  },
  {
    "Text": "Silky Cream",
    "StartAddress": 93544,
    "EndAddress": 93559,
    "MaxLength": 16
  },
  {
    "Text": "Super Silky Cream",
    "StartAddress": 93560,
    "EndAddress": 93583,
    "MaxLength": 24
  },
  {
    "Text": "Mega Silky Cream",
    "StartAddress": 93584,
    "EndAddress": 93607,
    "MaxLength": 24
  },
  {
    "Text": "Squid",
    "StartAddress": 93608,
    "EndAddress": 93615,
    "MaxLength": 8
  },
  {
    "Text": "Super Potion",
    "StartAddress": 93616,
    "EndAddress": 93631,
    "MaxLength": 16
  },
  {
    "Text": "Melba Toast",
    "StartAddress": 93632,
    "EndAddress": 93647,
    "MaxLength": 16
  },
  {
    "Text": "Powered Up Rod",
    "StartAddress": 93648,
    "EndAddress": 93663,
    "MaxLength": 16
  },
  {
    "Text": "Drained Power Rod",
    "StartAddress": 93664,
    "EndAddress": 93687,
    "MaxLength": 24
  },
  {
    "Text": "Automatically draws in nearby Gems and Hearts! ",
    "StartAddress": 93688,
    "EndAddress": 93735,
    "MaxLength": 48
  },
  {
    "Text": "Automatically draws in Gems and Hearts from a greater distance!",
    "StartAddress": 93736,
    "EndAddress": 93799,
    "MaxLength": 64
  },
  {
    "Text": "Automatically draws in Gems and Hearts from a significant distance!",
    "StartAddress": 93800,
    "EndAddress": 93871,
    "MaxLength": 72
  },
  {
    "Text": "A potion that kicks in when your Hearts run dry!",
    "StartAddress": 93872,
    "EndAddress": 93927,
    "MaxLength": 56
  },
  {
    "Text": "A value pack of everyone's favorite healing item!",
    "StartAddress": 93928,
    "EndAddress": 93983,
    "MaxLength": 56
  },
  {
    "Text": "Quickly <1>DODGE</1> enemy attacks! Press <IB action=Dodge scale=0.5 /> to dash!",
    "StartAddress": 93984,
    "EndAddress": 94071,
    "MaxLength": 88
  },
  {
    "Text": "Scientific evidence that proves... something!",
    "StartAddress": 94072,
    "EndAddress": 94119,
    "MaxLength": 48
  },
  {
    "Text": "We can learn a lot from the ocean, perhaps!",
    "StartAddress": 94120,
    "EndAddress": 94167,
    "MaxLength": 48
  },
  {
    "Text": "NA - boss key",
    "StartAddress": 94168,
    "EndAddress": 94183,
    "MaxLength": 16
  },
  {
    "Text": "An action figure based on Sequin Land's most famous superhero Bran-Son!",
    "StartAddress": 94184,
    "EndAddress": 94255,
    "MaxLength": 72
  },
  {
    "Text": "Processed food that restores small amount of health.",
    "StartAddress": 94256,
    "EndAddress": 94311,
    "MaxLength": 56
  },
  {
    "Text": "A list of <1>FIVE HALF-GENIES</1> who must be found! Check everywhere!",
    "StartAddress": 94312,
    "EndAddress": 94383,
    "MaxLength": 72
  },
  {
    "Text": "Introduce yourself to four more Half-Genie performers!",
    "StartAddress": 94384,
    "EndAddress": 94439,
    "MaxLength": 56
  },
  {
    "Text": "Introduce yourself to three more Half-Genie performers!",
    "StartAddress": 94440,
    "EndAddress": 94495,
    "MaxLength": 56
  },
  {
    "Text": "Introduce yourself to two more Half-Genie performers!",
    "StartAddress": 94496,
    "EndAddress": 94551,
    "MaxLength": 56
  },
  {
    "Text": "Introduce yourself to one more Half-Genie performer!",
    "StartAddress": 94552,
    "EndAddress": 94607,
    "MaxLength": 56
  },
  {
    "Text": "A gift from the Armor Baron to the mayor of Arena Town!",
    "StartAddress": 94608,
    "EndAddress": 94663,
    "MaxLength": 56
  },
  {
    "Text": "Success! Take it back to Arena Town's Mayor!",
    "StartAddress": 94664,
    "EndAddress": 94711,
    "MaxLength": 48
  },
  {
    "Text": "Increase the speed of the <1>TRANSFORMATION DANCES</1>!",
    "StartAddress": 94712,
    "EndAddress": 94767,
    "MaxLength": 56
  },
  {
    "Text": "The Ghost Elder near the sunken ships should see this!",
    "StartAddress": 94768,
    "EndAddress": 94823,
    "MaxLength": 56
  },
  {
    "Text": "Gastro Drill",
    "StartAddress": 94824,
    "EndAddress": 94839,
    "MaxLength": 16
  },
  {
    "Text": "Drill through the dirt!\nMove against a <1>SOFT SURFACE</1> to <1>DRILL</1>!",
    "StartAddress": 94840,
    "EndAddress": 94919,
    "MaxLength": 80
  },
  {
    "Text": "Drill through the dirt!\nPress against a <1>SOFT SURFACE</1> with <IB action=LSTICK scale=0.75/> to <1>DRILL</1>!",
    "StartAddress": 94920,
    "EndAddress": 95039,
    "MaxLength": 120
  },
  {
    "Text": "Bonker Tortoise",
    "StartAddress": 95040,
    "EndAddress": 95055,
    "MaxLength": 16
  },
  {
    "Text": "Swipe down on the screen in air to STOMP from above. You can also charge up and release <I anim=ui_global:ios_button_attack.anb scale=0.15/> to perform a destructive <1>SPIN DASH</1>!",
    "StartAddress": 95056,
    "EndAddress": 95239,
    "MaxLength": 184
  },
  {
    "Text": "Press <IB action=Stomp scale=0.75/> in air to <1>STOMP</1> from above. You can also charge up and release <IB action=Attack scale=0.75/> to perform a destructive <1>SPIN DASH</1>!",
    "StartAddress": 95240,
    "EndAddress": 95423,
    "MaxLength": 184
  },
  {
    "Text": "Sea Frog",
    "StartAddress": 95424,
    "EndAddress": 95439,
    "MaxLength": 16
  },
  {
    "Text": "Swim underwater! Hold <I anim=ui_global:ios_button_attack.anb scale=0.15/> to swim more slowly!",
    "StartAddress": 95440,
    "EndAddress": 95535,
    "MaxLength": 96
  },
  {
    "Text": "Use <IB action=LSTICK scale=0.75/> to move underwater! Hold <IB action=Attack scale=0.75/> to swim more slowly!",
    "StartAddress": 95536,
    "EndAddress": 95647,
    "MaxLength": 112
  },
  {
    "Text": "Fused Bracelet",
    "StartAddress": 95648,
    "EndAddress": 95663,
    "MaxLength": 16
  },
  {
    "Text": "A highly sought-after gemstone unique to this island!",
    "StartAddress": 95664,
    "EndAddress": 95719,
    "MaxLength": 56
  },
  {
    "Text": "Return this frightening doll to the Ghost Elder.",
    "StartAddress": 95720,
    "EndAddress": 95775,
    "MaxLength": 56
  },
  {
    "Text": "This doll's clothes suggest that it's from Armor Town. ",
    "StartAddress": 95776,
    "EndAddress": 95831,
    "MaxLength": 56
  },
  {
    "Text": "Legendary food that restores massive amounts of health.",
    "StartAddress": 95832,
    "EndAddress": 95887,
    "MaxLength": 56
  },
  {
    "Text": "Looks like it attaches to something nearby! ",
    "StartAddress": 95888,
    "EndAddress": 95935,
    "MaxLength": 48
  },
  {
    "Text": "Jet Octo",
    "StartAddress": 95936,
    "EndAddress": 95951,
    "MaxLength": 16
  },
  {
    "Text": "Press <I anim=ui_global:ios_button_jump.anb scale=0.15/> in air to get a <1>DOUBLE</1> or <1>TRIPLE</1> jump!",
    "StartAddress": 95952,
    "EndAddress": 96063,
    "MaxLength": 112
  },
  {
    "Text": "Press <IB action=Jump scale=0.75/> in air to get a <1>DOUBLE</1> or <1>TRIPLE</1> jump!",
    "StartAddress": 96064,
    "EndAddress": 96151,
    "MaxLength": 88
  },
  {
    "Text": "Refill your <1>HEARTS</1> with this handy potion!",
    "StartAddress": 96152,
    "EndAddress": 96207,
    "MaxLength": 56
  },
  {
    "Text": "A money-saving value pack of Potions!",
    "StartAddress": 96208,
    "EndAddress": 96247,
    "MaxLength": 40
  },
  {
    "Text": "Increases your <1>HEART CAPACITY</1>!",
    "StartAddress": 96248,
    "EndAddress": 96287,
    "MaxLength": 40
  },
  {
    "Text": "Take these to your local <1>SQUIDSMITH</1>!",
    "StartAddress": 96288,
    "EndAddress": 96335,
    "MaxLength": 48
  },
  {
    "Text": "Some kind of instructional manual. Useless.",
    "StartAddress": 96336,
    "EndAddress": 96383,
    "MaxLength": 48
  },
  {
    "Text": "Spray-on armor that lowers the amount of damage taken by 25%!",
    "StartAddress": 96384,
    "EndAddress": 96447,
    "MaxLength": 64
  },
  {
    "Text": "Used to open locked doors!",
    "StartAddress": 96448,
    "EndAddress": 96479,
    "MaxLength": 32
  },
  {
    "Text": "Return this to the friendly doggo!",
    "StartAddress": 96480,
    "EndAddress": 96519,
    "MaxLength": 40
  },
  {
    "Text": "Plink is waiting backstage for one of these!",
    "StartAddress": 96520,
    "EndAddress": 96567,
    "MaxLength": 48
  },
  {
    "Text": "Refill your <1>MAGIC METER</1> with this handy potion!",
    "StartAddress": 96568,
    "EndAddress": 96623,
    "MaxLength": 56
  },
  {
    "Text": "Save your gems! Buy in volume!",
    "StartAddress": 96624,
    "EndAddress": 96655,
    "MaxLength": 32
  },
  {
    "Text": "A soft, hand made doll with buttons on it.",
    "StartAddress": 96656,
    "EndAddress": 96703,
    "MaxLength": 48
  },
  {
    "Text": "A map to the current location!",
    "StartAddress": 96704,
    "EndAddress": 96735,
    "MaxLength": 32
  },
  {
    "Text": "Wasn't <1>VERA</1> asking about something like this?",
    "StartAddress": 96736,
    "EndAddress": 96791,
    "MaxLength": 56
  },
  {
    "Text": "Bring <1>SIX SHELLS</1> to the scientist! Collect 5 more!",
    "StartAddress": 96792,
    "EndAddress": 96855,
    "MaxLength": 64
  },
  {
    "Text": "Bring <1>SIX SHELLS</1> to the scientist! Collect 4 more!",
    "StartAddress": 96856,
    "EndAddress": 96919,
    "MaxLength": 64
  },
  {
    "Text": "Bring <1>SIX SHELLS</1> to the scientist! Collect 3 more!",
    "StartAddress": 96920,
    "EndAddress": 96983,
    "MaxLength": 64
  },
  {
    "Text": "Bring <1>SIX SHELLS</1> to the scientist! Collect 2 more!",
    "StartAddress": 96984,
    "EndAddress": 97047,
    "MaxLength": 64
  },
  {
    "Text": "Bring <1>SIX SHELLS</1> to the scientist! Collect 1 more!",
    "StartAddress": 97048,
    "EndAddress": 97111,
    "MaxLength": 64
  },
  {
    "Text": "You found all <1>SIX SHELLS</1>! Take them to the scientist!",
    "StartAddress": 97112,
    "EndAddress": 97175,
    "MaxLength": 64
  },
  {
    "Text": "Dash Newt",
    "StartAddress": 97176,
    "EndAddress": 97191,
    "MaxLength": 16
  },
  {
    "Text": "Dash and climb walls as a newt!\nPress <I anim=ui_global:ios_button_fusion.anb scale=0.25/> in air to <1>DASH</1>.",
    "StartAddress": 97192,
    "EndAddress": 97311,
    "MaxLength": 120
  },
  {
    "Text": "Dash and climb walls as a newt!\nPress <IB action=Dash scale=0.75/> in air to <1>DASH</1>.",
    "StartAddress": 97312,
    "EndAddress": 97407,
    "MaxLength": 96
  },
  {
    "Text": "Reduces your <1>MAGIC</1> consumption.",
    "StartAddress": 97408,
    "EndAddress": 97447,
    "MaxLength": 40
  },
  {
    "Text": "Only the Champ of Legend can find all <1>THREE DAGRON BALLS</1>! Patent pending.",
    "StartAddress": 97448,
    "EndAddress": 97535,
    "MaxLength": 88
  },
  {
    "Text": "Tasty food that restores health.",
    "StartAddress": 97536,
    "EndAddress": 97575,
    "MaxLength": 40
  },
  {
    "Text": "Metal Ore for the Armor Baron! He needs three of these.",
    "StartAddress": 97576,
    "EndAddress": 97631,
    "MaxLength": 56
  },
  {
    "Text": "Well-prepared food that restores a good amount of health.",
    "StartAddress": 97632,
    "EndAddress": 97695,
    "MaxLength": 64
  },
  {
    "Text": "Increase the <1>DAMAGE DEALT</1> by your hair!",
    "StartAddress": 97696,
    "EndAddress": 97743,
    "MaxLength": 48
  },
  {
    "Text": "Increase the <1>DAMAGE DEALT</1> by your hair!",
    "StartAddress": 97744,
    "EndAddress": 97791,
    "MaxLength": 48
  },
  {
    "Text": "Increase the <1>DAMAGE DEALT</1> by your hair!",
    "StartAddress": 97792,
    "EndAddress": 97839,
    "MaxLength": 48
  },
  {
    "Text": "Take this to the Control Room. Ghost Dog knows the way!",
    "StartAddress": 97840,
    "EndAddress": 97895,
    "MaxLength": 56
  },
  {
    "Text": "Tangy food that restores a lot of health.",
    "StartAddress": 97896,
    "EndAddress": 97943,
    "MaxLength": 48
  },
  {
    "Text": "Spare parts that can be used to repair a broken electric machine.",
    "StartAddress": 97944,
    "EndAddress": 98015,
    "MaxLength": 72
  },
  {
    "Text": "Return this to the friendly doggo!",
    "StartAddress": 98016,
    "EndAddress": 98055,
    "MaxLength": 40
  },
  {
    "Text": "Tasty food that restores health.",
    "StartAddress": 98056,
    "EndAddress": 98095,
    "MaxLength": 40
  },
  {
    "Text": "Roasted fruit that restores a fair amount of health.",
    "StartAddress": 98096,
    "EndAddress": 98151,
    "MaxLength": 56
  },
  {
    "Text": "The words WEST HATCH are inscribed on it.",
    "StartAddress": 98152,
    "EndAddress": 98199,
    "MaxLength": 48
  },
  {
    "Text": "Expertly-prepared food that restores a ton of health.",
    "StartAddress": 98200,
    "EndAddress": 98255,
    "MaxLength": 56
  },
  {
    "Text": "Increase the <1>WHIPPING SPEED</1> of your hair!",
    "StartAddress": 98256,
    "EndAddress": 98311,
    "MaxLength": 56
  },
  {
    "Text": "Increase the <1>WHIPPING SPEED</1> of your hair!",
    "StartAddress": 98312,
    "EndAddress": 98367,
    "MaxLength": 56
  },
  {
    "Text": "Increase the <1>WHIPPING SPEED</1> of your hair!",
    "StartAddress": 98368,
    "EndAddress": 98423,
    "MaxLength": 56
  },
  {
    "Text": "Take these to the Squidsmith back in town!",
    "StartAddress": 98424,
    "EndAddress": 98471,
    "MaxLength": 48
  },
  {
    "Text": "Refills <1>HEARTS AND MAGIC</1>! What a deal!",
    "StartAddress": 98472,
    "EndAddress": 98519,
    "MaxLength": 48
  },
  {
    "Text": "Buy in bulk! Refill Hearts and Magic with one gulp!",
    "StartAddress": 98520,
    "EndAddress": 98575,
    "MaxLength": 56
  },
  {
    "Text": "Crunchy toast that's been stepped on. Bolo's favorite.",
    "StartAddress": 98576,
    "EndAddress": 98631,
    "MaxLength": 56
  },
  {
    "Text": "Some kind of energy conductor. But it's out of power.",
    "StartAddress": 98632,
    "EndAddress": 98687,
    "MaxLength": 56
  },
  {
    "Text": "Bat",
    "StartAddress": 98688,
    "EndAddress": 98695,
    "MaxLength": 8
  },
  {
    "Text": "Crab",
    "StartAddress": 98696,
    "EndAddress": 98703,
    "MaxLength": 8
  },
  {
    "Text": "Slime",
    "StartAddress": 98704,
    "EndAddress": 98711,
    "MaxLength": 8
  },
  {
    "Text": "Tree Troll",
    "StartAddress": 98712,
    "EndAddress": 98727,
    "MaxLength": 16
  },
  {
    "Text": "Slime Wiz",
    "StartAddress": 98728,
    "EndAddress": 98743,
    "MaxLength": 16
  },
  {
    "Text": "Siren Man",
    "StartAddress": 98744,
    "EndAddress": 98759,
    "MaxLength": 16
  },
  {
    "Text": "Archer",
    "StartAddress": 98760,
    "EndAddress": 98767,
    "MaxLength": 8
  },
  {
    "Text": "Crystal Crab",
    "StartAddress": 98768,
    "EndAddress": 98783,
    "MaxLength": 16
  },
  {
    "Text": "Orc",
    "StartAddress": 98784,
    "EndAddress": 98791,
    "MaxLength": 8
  },
  {
    "Text": "Snake",
    "StartAddress": 98792,
    "EndAddress": 98799,
    "MaxLength": 8
  },
  {
    "Text": "Eagle Man Bomber",
    "StartAddress": 98800,
    "EndAddress": 98823,
    "MaxLength": 24
  },
  {
    "Text": "Froglips",
    "StartAddress": 98824,
    "EndAddress": 98839,
    "MaxLength": 16
  },
  {
    "Text": "Pincher",
    "StartAddress": 98840,
    "EndAddress": 98847,
    "MaxLength": 8
  },
  {
    "Text": "Naga",
    "StartAddress": 98848,
    "EndAddress": 98855,
    "MaxLength": 8
  },
  {
    "Text": "Cactus",
    "StartAddress": 98856,
    "EndAddress": 98863,
    "MaxLength": 8
  },
  {
    "Text": "Scorpgal",
    "StartAddress": 98864,
    "EndAddress": 98879,
    "MaxLength": 16
  },
  {
    "Text": "Scorpman",
    "StartAddress": 98880,
    "EndAddress": 98895,
    "MaxLength": 16
  },
  {
    "Text": "Bone Fish",
    "StartAddress": 98896,
    "EndAddress": 98911,
    "MaxLength": 16
  },
  {
    "Text": "Wetman",
    "StartAddress": 98912,
    "EndAddress": 98919,
    "MaxLength": 8
  },
  {
    "Text": "Wetgal",
    "StartAddress": 98920,
    "EndAddress": 98927,
    "MaxLength": 8
  },
  {
    "Text": "Mermaid",
    "StartAddress": 98928,
    "EndAddress": 98935,
    "MaxLength": 8
  },
  {
    "Text": "Jellyfish",
    "StartAddress": 98936,
    "EndAddress": 98951,
    "MaxLength": 16
  },
  {
    "Text": "Lobster Jogger",
    "StartAddress": 98952,
    "EndAddress": 98967,
    "MaxLength": 16
  },
  {
    "Text": "Ceiling Bug",
    "StartAddress": 98968,
    "EndAddress": 98983,
    "MaxLength": 16
  },
  {
    "Text": "Golem",
    "StartAddress": 98984,
    "EndAddress": 98991,
    "MaxLength": 8
  },
  {
    "Text": "Rocket Archer",
    "StartAddress": 98992,
    "EndAddress": 99007,
    "MaxLength": 16
  },
  {
    "Text": "Muckgal",
    "StartAddress": 99008,
    "EndAddress": 99015,
    "MaxLength": 8
  },
  {
    "Text": "Muckman",
    "StartAddress": 99016,
    "EndAddress": 99023,
    "MaxLength": 8
  },
  {
    "Text": "Phase Wall Dasher",
    "StartAddress": 99024,
    "EndAddress": 99047,
    "MaxLength": 24
  },
  {
    "Text": "Spider",
    "StartAddress": 99048,
    "EndAddress": 99055,
    "MaxLength": 8
  },
  {
    "Text": "Dirt Crawler",
    "StartAddress": 99056,
    "EndAddress": 99071,
    "MaxLength": 16
  },
  {
    "Text": "Ghost Eye",
    "StartAddress": 99072,
    "EndAddress": 99087,
    "MaxLength": 16
  },
  {
    "Text": "Spectre",
    "StartAddress": 99088,
    "EndAddress": 99095,
    "MaxLength": 8
  },
  {
    "Text": "Skeleton Knight",
    "StartAddress": 99096,
    "EndAddress": 99111,
    "MaxLength": 16
  },
  {
    "Text": "Sickly Silverfish",
    "StartAddress": 99112,
    "EndAddress": 99135,
    "MaxLength": 24
  },
  {
    "Text": "Batgal",
    "StartAddress": 99136,
    "EndAddress": 99143,
    "MaxLength": 8
  },
  {
    "Text": "Dragon Head",
    "StartAddress": 99144,
    "EndAddress": 99159,
    "MaxLength": 16
  },
  {
    "Text": "Jumping Frog",
    "StartAddress": 99160,
    "EndAddress": 99175,
    "MaxLength": 16
  },
  {
    "Text": "Wall Dasher",
    "StartAddress": 99176,
    "EndAddress": 99191,
    "MaxLength": 16
  },
  {
    "Text": "Circus Squid",
    "StartAddress": 99192,
    "EndAddress": 99207,
    "MaxLength": 16
  },
  {
    "Text": "Rag and Bones",
    "StartAddress": 99208,
    "EndAddress": 99223,
    "MaxLength": 16
  },
  {
    "Text": "Metal Slag",
    "StartAddress": 99224,
    "EndAddress": 99239,
    "MaxLength": 16
  },
  {
    "Text": "Siren Soldier",
    "StartAddress": 99240,
    "EndAddress": 99255,
    "MaxLength": 16
  },
  {
    "Text": "Water Lily Siren",
    "StartAddress": 99256,
    "EndAddress": 99279,
    "MaxLength": 24
  },
  {
    "Text": "Coral Siren",
    "StartAddress": 99280,
    "EndAddress": 99295,
    "MaxLength": 16
  },
  {
    "Text": "Tubeworm Siren",
    "StartAddress": 99296,
    "EndAddress": 99311,
    "MaxLength": 16
  },
  {
    "Text": "Angler Fish Siren",
    "StartAddress": 99312,
    "EndAddress": 99335,
    "MaxLength": 24
  },
  {
    "Text": "Octo Siren",
    "StartAddress": 99336,
    "EndAddress": 99351,
    "MaxLength": 16
  },
  {
    "Text": "Empress",
    "StartAddress": 99352,
    "EndAddress": 99359,
    "MaxLength": 8
  },
  {
    "Text": "Lobster Girl",
    "StartAddress": 99360,
    "EndAddress": 99375,
    "MaxLength": 16
  },
  {
    "Text": "Equipped Cards",
    "StartAddress": 99376,
    "EndAddress": 99391,
    "MaxLength": 16
  },
  {
    "Text": "Cards Collected",
    "StartAddress": 99392,
    "EndAddress": 99407,
    "MaxLength": 16
  },
  {
    "Text": "Crawl Speed +",
    "StartAddress": 99408,
    "EndAddress": 99423,
    "MaxLength": 16
  },
  {
    "Text": "Crawl much faster than before!",
    "StartAddress": 99424,
    "EndAddress": 99455,
    "MaxLength": 32
  },
  {
    "Text": "Swim Speed +",
    "StartAddress": 99456,
    "EndAddress": 99471,
    "MaxLength": 16
  },
  {
    "Text": "Swim with super speed!",
    "StartAddress": 99472,
    "EndAddress": 99495,
    "MaxLength": 24
  },
  {
    "Text": "Rope Speed +",
    "StartAddress": 99496,
    "EndAddress": 99511,
    "MaxLength": 16
  },
  {
    "Text": "Greatly increase your climbing speed!",
    "StartAddress": 99512,
    "EndAddress": 99551,
    "MaxLength": 40
  },
  {
    "Text": "No Pit Damage",
    "StartAddress": 99552,
    "EndAddress": 99567,
    "MaxLength": 16
  },
  {
    "Text": "Take no damage when destroyed by a pit!",
    "StartAddress": 99568,
    "EndAddress": 99607,
    "MaxLength": 40
  },
  {
    "Text": "No Spike Damage",
    "StartAddress": 99608,
    "EndAddress": 99623,
    "MaxLength": 16
  },
  {
    "Text": "Take zero damage when destroyed by spikes!",
    "StartAddress": 99624,
    "EndAddress": 99671,
    "MaxLength": 48
  },
  {
    "Text": "Hair Whip +",
    "StartAddress": 99672,
    "EndAddress": 99687,
    "MaxLength": 16
  },
  {
    "Text": "Hair Whip attack deals even more damage than before!",
    "StartAddress": 99688,
    "EndAddress": 99743,
    "MaxLength": 56
  },
  {
    "Text": "Damage Taken -",
    "StartAddress": 99744,
    "EndAddress": 99759,
    "MaxLength": 16
  },
  {
    "Text": "Reduce the amount of damage taken from enemy attacks!",
    "StartAddress": 99760,
    "EndAddress": 99815,
    "MaxLength": 56
  },
  {
    "Text": "Magic Regen",
    "StartAddress": 99816,
    "EndAddress": 99831,
    "MaxLength": 16
  },
  {
    "Text": "The Magic Meter will refill over time!",
    "StartAddress": 99832,
    "EndAddress": 99871,
    "MaxLength": 40
  },
  {
    "Text": "Food Power +",
    "StartAddress": 99872,
    "EndAddress": 99887,
    "MaxLength": 16
  },
  {
    "Text": "All food types gain an extra healing boost when consumed!",
    "StartAddress": 99888,
    "EndAddress": 99951,
    "MaxLength": 64
  },
  {
    "Text": "Attract Distance +",
    "StartAddress": 99952,
    "EndAddress": 99975,
    "MaxLength": 24
  },
  {
    "Text": "Loot will be automatically drawn in from a greater distance!",
    "StartAddress": 99976,
    "EndAddress": 100039,
    "MaxLength": 64
  },
  {
    "Text": "Dash Damage +",
    "StartAddress": 100040,
    "EndAddress": 100055,
    "MaxLength": 16
  },
  {
    "Text": "Inflict even more damage when using the Newt Dash!",
    "StartAddress": 100056,
    "EndAddress": 100111,
    "MaxLength": 56
  },
  {
    "Text": "Dash Distance +",
    "StartAddress": 100112,
    "EndAddress": 100127,
    "MaxLength": 16
  },
  {
    "Text": "Extend the reach of the Newt Dash and fly further!",
    "StartAddress": 100128,
    "EndAddress": 100183,
    "MaxLength": 56
  },
  {
    "Text": "Dash Speed +",
    "StartAddress": 100184,
    "EndAddress": 100199,
    "MaxLength": 16
  },
  {
    "Text": "The Newt travels at super speed when dashing!",
    "StartAddress": 100200,
    "EndAddress": 100247,
    "MaxLength": 48
  },
  {
    "Text": "Newt Climb +",
    "StartAddress": 100248,
    "EndAddress": 100263,
    "MaxLength": 16
  },
  {
    "Text": "Zip up walls with reckless abandon as the Newt!",
    "StartAddress": 100264,
    "EndAddress": 100311,
    "MaxLength": 48
  },
  {
    "Text": "Drill Speed +",
    "StartAddress": 100312,
    "EndAddress": 100327,
    "MaxLength": 16
  },
  {
    "Text": "Drill through dirt much faster than before!",
    "StartAddress": 100328,
    "EndAddress": 100375,
    "MaxLength": 48
  },
  {
    "Text": "Bash Damage +",
    "StartAddress": 100376,
    "EndAddress": 100391,
    "MaxLength": 16
  },
  {
    "Text": "The Tortoise's Bash attack causes higher damage than before!",
    "StartAddress": 100392,
    "EndAddress": 100455,
    "MaxLength": 64
  },
  {
    "Text": "Stomp Damage +",
    "StartAddress": 100456,
    "EndAddress": 100471,
    "MaxLength": 16
  },
  {
    "Text": "Deal more damage to foes using super powerful Tortoise Stomps!",
    "StartAddress": 100472,
    "EndAddress": 100535,
    "MaxLength": 64
  },
  {
    "Text": "Charge Time -",
    "StartAddress": 100536,
    "EndAddress": 100551,
    "MaxLength": 16
  },
  {
    "Text": "The Tortoise Form will take less time to charge up!",
    "StartAddress": 100552,
    "EndAddress": 100607,
    "MaxLength": 56
  },
  {
    "Text": "Frog Speed +",
    "StartAddress": 100608,
    "EndAddress": 100623,
    "MaxLength": 16
  },
  {
    "Text": "Frog speed will drastically increase!",
    "StartAddress": 100624,
    "EndAddress": 100663,
    "MaxLength": 40
  },
  {
    "Text": "Seer Cost -",
    "StartAddress": 100664,
    "EndAddress": 100679,
    "MaxLength": 16
  },
  {
    "Text": "The Seer Dance consumes less magic when used!",
    "StartAddress": 100680,
    "EndAddress": 100727,
    "MaxLength": 48
  },
  {
    "Text": "Refresh Cost -",
    "StartAddress": 100728,
    "EndAddress": 100743,
    "MaxLength": 16
  },
  {
    "Text": "The Refresh Dance consumes less magic when used!",
    "StartAddress": 100744,
    "EndAddress": 100799,
    "MaxLength": 56
  },
  {
    "Text": "Refresh Healing +",
    "StartAddress": 100800,
    "EndAddress": 100823,
    "MaxLength": 24
  },
  {
    "Text": "The Refresh Dance restores more Empty Hearts than before!",
    "StartAddress": 100824,
    "EndAddress": 100887,
    "MaxLength": 64
  },
  {
    "Text": "Refresh Damage +",
    "StartAddress": 100888,
    "EndAddress": 100911,
    "MaxLength": 24
  },
  {
    "Text": "The Refresh Dance does more damage to sickly or undead foes!",
    "StartAddress": 100912,
    "EndAddress": 100975,
    "MaxLength": 64
  },
  {
    "Text": "Electric Cost -",
    "StartAddress": 100976,
    "EndAddress": 100991,
    "MaxLength": 16
  },
  {
    "Text": "The Spark Dance consumes less magic when used!",
    "StartAddress": 100992,
    "EndAddress": 101039,
    "MaxLength": 48
  },
  {
    "Text": "Electric Power +",
    "StartAddress": 101040,
    "EndAddress": 101063,
    "MaxLength": 24
  },
  {
    "Text": "The Spark Dance does more damage to foes!",
    "StartAddress": 101064,
    "EndAddress": 101111,
    "MaxLength": 48
  },
  {
    "Text": "Quake Cost -",
    "StartAddress": 101112,
    "EndAddress": 101127,
    "MaxLength": 16
  },
  {
    "Text": "The Quake Dance consumes less magic when used!",
    "StartAddress": 101128,
    "EndAddress": 101175,
    "MaxLength": 48
  },
  {
    "Text": "Quake Power +",
    "StartAddress": 101176,
    "EndAddress": 101191,
    "MaxLength": 16
  },
  {
    "Text": "The Quake Dance does more damage to foes!",
    "StartAddress": 101192,
    "EndAddress": 101239,
    "MaxLength": 48
  },
  {
    "Text": "Rocket Damage +",
    "StartAddress": 101240,
    "EndAddress": 101255,
    "MaxLength": 16
  },
  {
    "Text": "Rockets inflict more damage to their targets!",
    "StartAddress": 101256,
    "EndAddress": 101303,
    "MaxLength": 48
  },
  {
    "Text": "Rocket Speed +",
    "StartAddress": 101304,
    "EndAddress": 101319,
    "MaxLength": 16
  },
  {
    "Text": "Rockets travel much faster when chasing down their targets!",
    "StartAddress": 101320,
    "EndAddress": 101383,
    "MaxLength": 64
  },
  {
    "Text": "Rocket Cost -",
    "StartAddress": 101384,
    "EndAddress": 101399,
    "MaxLength": 16
  },
  {
    "Text": "Rockets consumes less magic when used!",
    "StartAddress": 101400,
    "EndAddress": 101439,
    "MaxLength": 40
  },
  {
    "Text": "Super Ball +",
    "StartAddress": 101440,
    "EndAddress": 101455,
    "MaxLength": 16
  },
  {
    "Text": "Increase the damage dealt by the bouncing Super Ball weapon!",
    "StartAddress": 101456,
    "EndAddress": 101519,
    "MaxLength": 64
  },
  {
    "Text": "Super Ball Speed +",
    "StartAddress": 101520,
    "EndAddress": 101543,
    "MaxLength": 24
  },
  {
    "Text": "The Super Ball travels much faster than before!",
    "StartAddress": 101544,
    "EndAddress": 101591,
    "MaxLength": 48
  },
  {
    "Text": "Super Ball Cost -",
    "StartAddress": 101592,
    "EndAddress": 101615,
    "MaxLength": 24
  },
  {
    "Text": "The Super Ball consumes less magic when used!",
    "StartAddress": 101616,
    "EndAddress": 101663,
    "MaxLength": 48
  },
  {
    "Text": "Fireball Damage +",
    "StartAddress": 101664,
    "EndAddress": 101687,
    "MaxLength": 24
  },
  {
    "Text": "Increase the damage caused by Fireball magic!",
    "StartAddress": 101688,
    "EndAddress": 101735,
    "MaxLength": 48
  },
  {
    "Text": "Fireball Cost -",
    "StartAddress": 101736,
    "EndAddress": 101751,
    "MaxLength": 16
  },
  {
    "Text": "Fireballs consume less magic when used!",
    "StartAddress": 101752,
    "EndAddress": 101791,
    "MaxLength": 40
  },
  {
    "Text": "Shield Cost -",
    "StartAddress": 101792,
    "EndAddress": 101807,
    "MaxLength": 16
  },
  {
    "Text": "The Shield consumes less magic when used!",
    "StartAddress": 101808,
    "EndAddress": 101855,
    "MaxLength": 48
  },
  {
    "Text": "Boomerang Damage +",
    "StartAddress": 101856,
    "EndAddress": 101879,
    "MaxLength": 24
  },
  {
    "Text": "The Boomerang does more damage than before!",
    "StartAddress": 101880,
    "EndAddress": 101927,
    "MaxLength": 48
  },
  {
    "Text": "Boomerang Speed +",
    "StartAddress": 101928,
    "EndAddress": 101951,
    "MaxLength": 24
  },
  {
    "Text": "Boomerangs are thrown with tremendous speed!",
    "StartAddress": 101952,
    "EndAddress": 101999,
    "MaxLength": 48
  },
  {
    "Text": "Boomerang Cost -",
    "StartAddress": 102000,
    "EndAddress": 102023,
    "MaxLength": 24
  },
  {
    "Text": "The Boomerang consumes less magic when used!",
    "StartAddress": 102024,
    "EndAddress": 102071,
    "MaxLength": 48
  },
  {
    "Text": "Pike Ball Damage +",
    "StartAddress": 102072,
    "EndAddress": 102095,
    "MaxLength": 24
  },
  {
    "Text": "The Pike Ball weapon class deals even more damage to foes!",
    "StartAddress": 102096,
    "EndAddress": 102159,
    "MaxLength": 64
  },
  {
    "Text": "Pike Ball Cost -",
    "StartAddress": 102160,
    "EndAddress": 102183,
    "MaxLength": 24
  },
  {
    "Text": "The Pike Ball consumes less magic when used!",
    "StartAddress": 102184,
    "EndAddress": 102231,
    "MaxLength": 48
  },
  {
    "Text": "Heart Luck +",
    "StartAddress": 102232,
    "EndAddress": 102247,
    "MaxLength": 16
  },
  {
    "Text": "Increase the odds of collecting dropped Hearts!",
    "StartAddress": 102248,
    "EndAddress": 102295,
    "MaxLength": 48
  },
  {
    "Text": "Food Luck +",
    "StartAddress": 102296,
    "EndAddress": 102311,
    "MaxLength": 16
  },
  {
    "Text": "Increase the odds of collecting dropped Food!",
    "StartAddress": 102312,
    "EndAddress": 102359,
    "MaxLength": 48
  },
  {
    "Text": "Gem Pickups Increase",
    "StartAddress": 102360,
    "EndAddress": 102383,
    "MaxLength": 24
  },
  {
    "Text": "Increase the number of dropped Gems!",
    "StartAddress": 102384,
    "EndAddress": 102423,
    "MaxLength": 40
  },
  {
    "Text": "Magic Pickups Increase",
    "StartAddress": 102424,
    "EndAddress": 102447,
    "MaxLength": 24
  },
  {
    "Text": "Increase the odds of collecting dropped Magic!",
    "StartAddress": 102448,
    "EndAddress": 102495,
    "MaxLength": 48
  },
  {
    "Text": "Discount Card",
    "StartAddress": 102496,
    "EndAddress": 102511,
    "MaxLength": 16
  },
  {
    "Text": "Get reduced prices at any Item Shop!",
    "StartAddress": 102512,
    "EndAddress": 102551,
    "MaxLength": 40
  },
  {
    "Text": "Pincher Power",
    "StartAddress": 102552,
    "EndAddress": 102567,
    "MaxLength": 16
  },
  {
    "Text": "Gain Shell-cracking strength that can defeat even Pincher monsters!",
    "StartAddress": 102568,
    "EndAddress": 102639,
    "MaxLength": 72
  },
  {
    "Text": "Jug Buster",
    "StartAddress": 102640,
    "EndAddress": 102655,
    "MaxLength": 16
  },
  {
    "Text": "Automatically break jugs by walking into them!",
    "StartAddress": 102656,
    "EndAddress": 102703,
    "MaxLength": 48
  },
  {
    "Text": "Red Gem Converter",
    "StartAddress": 102704,
    "EndAddress": 102727,
    "MaxLength": 24
  },
  {
    "Text": "Use your Hair Whip to convert Red Gems into Hearts!",
    "StartAddress": 102728,
    "EndAddress": 102783,
    "MaxLength": 56
  },
  {
    "Text": "Green Gem Converter",
    "StartAddress": 102784,
    "EndAddress": 102807,
    "MaxLength": 24
  },
  {
    "Text": "Use your Hair Whip to convert Green Gems into Magic!",
    "StartAddress": 102808,
    "EndAddress": 102863,
    "MaxLength": 56
  },
  {
    "Text": "This card can't be identified at this time!",
    "StartAddress": 102864,
    "EndAddress": 102911,
    "MaxLength": 48
  },
  {
    "Text": "This card's abilities remain a mystery!",
    "StartAddress": 102912,
    "EndAddress": 102951,
    "MaxLength": 40
  },
  {
    "Text": "Seer Dance",
    "StartAddress": 102952,
    "EndAddress": 102967,
    "MaxLength": 16
  },
  {
    "Text": "Refresh Dance",
    "StartAddress": 102968,
    "EndAddress": 102983,
    "MaxLength": 16
  },
  {
    "Text": "Quake Dance",
    "StartAddress": 102984,
    "EndAddress": 102999,
    "MaxLength": 16
  },
  {
    "Text": "Spark Dance",
    "StartAddress": 103000,
    "EndAddress": 103015,
    "MaxLength": 16
  },
  {
    "Text": "This mysterious dance can reveal things that are hidden from the naked eye! Try using it in a variety of places! ",
    "StartAddress": 103016,
    "EndAddress": 103135,
    "MaxLength": 120
  },
  {
    "Text": "The power of nature can revive the weary and heal the sick - and restore Empty Hearts in the process!",
    "StartAddress": 103136,
    "EndAddress": 103239,
    "MaxLength": 104
  },
  {
    "Text": "Shake things up by calling forth powerful tremors! This dance deals heavy damage, and can even alter your surroundings...",
    "StartAddress": 103240,
    "EndAddress": 103367,
    "MaxLength": 128
  },
  {
    "Text": "Shock your foes with the power of this electrical dance. It may affect other objects as well... ",
    "StartAddress": 103368,
    "EndAddress": 103471,
    "MaxLength": 104
  },
  {
    "Text": "Bubble",
    "StartAddress": 103472,
    "EndAddress": 103479,
    "MaxLength": 8
  },
  {
    "Text": "Fireball",
    "StartAddress": 103480,
    "EndAddress": 103495,
    "MaxLength": 16
  },
  {
    "Text": "Flamethrower",
    "StartAddress": 103496,
    "EndAddress": 103511,
    "MaxLength": 16
  },
  {
    "Text": "Pike Ball",
    "StartAddress": 103512,
    "EndAddress": 103527,
    "MaxLength": 16
  },
  {
    "Text": "Super Pike Ball",
    "StartAddress": 103528,
    "EndAddress": 103543,
    "MaxLength": 16
  },
  {
    "Text": "Triple Fireball",
    "StartAddress": 103544,
    "EndAddress": 103559,
    "MaxLength": 16
  },
  {
    "Text": "Scimitar",
    "StartAddress": 103560,
    "EndAddress": 103575,
    "MaxLength": 16
  },
  {
    "Text": "Mirror Shield",
    "StartAddress": 103576,
    "EndAddress": 103591,
    "MaxLength": 16
  },
  {
    "Text": "Invincibility",
    "StartAddress": 103592,
    "EndAddress": 103607,
    "MaxLength": 16
  },
  {
    "Text": "Super Ball 1",
    "StartAddress": 103608,
    "EndAddress": 103623,
    "MaxLength": 16
  },
  {
    "Text": "Super Ball 2",
    "StartAddress": 103624,
    "EndAddress": 103639,
    "MaxLength": 16
  },
  {
    "Text": "Super Ball 3",
    "StartAddress": 103640,
    "EndAddress": 103655,
    "MaxLength": 16
  },
  {
    "Text": "Homing Rocket 1",
    "StartAddress": 103656,
    "EndAddress": 103671,
    "MaxLength": 16
  },
  {
    "Text": "Homing Rocket 2",
    "StartAddress": 103672,
    "EndAddress": 103687,
    "MaxLength": 16
  },
  {
    "Text": "Homing Rocket 3",
    "StartAddress": 103688,
    "EndAddress": 103703,
    "MaxLength": 16
  },
  {
    "Text": "Boomerang",
    "StartAddress": 103704,
    "EndAddress": 103719,
    "MaxLength": 16
  },
  {
    "Text": "Double Boomerang",
    "StartAddress": 103720,
    "EndAddress": 103743,
    "MaxLength": 24
  },
  {
    "Text": "Triple Boomerang",
    "StartAddress": 103744,
    "EndAddress": 103767,
    "MaxLength": 24
  },
  {
    "Text": "Protect yourself from enemy projectiles with a <1>BUBBLE</1> shield! ",
    "StartAddress": 103768,
    "EndAddress": 103839,
    "MaxLength": 72
  },
  {
    "Text": "Spend <1>MAGIC</1> to roast your foes from <1>LONG RANGE</1>!",
    "StartAddress": 103840,
    "EndAddress": 103903,
    "MaxLength": 64
  },
  {
    "Text": "Bring on the <1>SIZZLE</1> with heavy duty <1>FIREPOWER</1>! Consumes <1>MAGIC</1>.",
    "StartAddress": 103904,
    "EndAddress": 103991,
    "MaxLength": 88
  },
  {
    "Text": "An <1>ORBITING BALL</1> protects your bod! Consumes <1>MAGIC</1>.",
    "StartAddress": 103992,
    "EndAddress": 104063,
    "MaxLength": 72
  },
  {
    "Text": "Three <1>STEEL BALLS</1> orbit your body! Uses <1>MAGIC</1>.",
    "StartAddress": 104064,
    "EndAddress": 104127,
    "MaxLength": 64
  },
  {
    "Text": "Even more <1>FIREBALL</1> coverage than before! Consumes <1>MAGIC</1>.",
    "StartAddress": 104128,
    "EndAddress": 104199,
    "MaxLength": 72
  },
  {
    "Text": "Arm yourself with the mystical power of orbiting <1>SCIMITAR</1> blades!",
    "StartAddress": 104200,
    "EndAddress": 104279,
    "MaxLength": 80
  },
  {
    "Text": "Repel attacks with this powerful shield!",
    "StartAddress": 104280,
    "EndAddress": 104327,
    "MaxLength": 48
  },
  {
    "Text": "Shrug off enemy attacks with total invincibility! ",
    "StartAddress": 104328,
    "EndAddress": 104383,
    "MaxLength": 56
  },
  {
    "Text": "Launch a bouncing projectile to hit foes at awkward angles! Boing!",
    "StartAddress": 104384,
    "EndAddress": 104455,
    "MaxLength": 72
  },
  {
    "Text": "Throw two of these powerful, rebounding balls at a time! ",
    "StartAddress": 104456,
    "EndAddress": 104519,
    "MaxLength": 64
  },
  {
    "Text": "Throw three bouncing balls! Enemies, there's no escape! ",
    "StartAddress": 104520,
    "EndAddress": 104583,
    "MaxLength": 64
  },
  {
    "Text": "Fire deadly projectiles that seek out targets on their own! ",
    "StartAddress": 104584,
    "EndAddress": 104647,
    "MaxLength": 64
  },
  {
    "Text": "Increase the number, speed, and damage of these heat-seeking beauties!",
    "StartAddress": 104648,
    "EndAddress": 104719,
    "MaxLength": 72
  },
  {
    "Text": "Max out your rockets with top tier speed and damage!",
    "StartAddress": 104720,
    "EndAddress": 104775,
    "MaxLength": 56
  },
  {
    "Text": "Cast a wooden projectile that always comes back!",
    "StartAddress": 104776,
    "EndAddress": 104831,
    "MaxLength": 56
  },
  {
    "Text": "Cast two Boomerangs at a time, in a wide array.",
    "StartAddress": 104832,
    "EndAddress": 104879,
    "MaxLength": 48
  },
  {
    "Text": "Triple the fun! Cast a sweep of Boomerangs and slice your foes to bits!",
    "StartAddress": 104880,
    "EndAddress": 104951,
    "MaxLength": 72
  },
  {
    "Text": "Would you like to warp to %s?",
    "StartAddress": 104952,
    "EndAddress": 104983,
    "MaxLength": 32
  },
  {
    "Text": "You unlocked a Secret Gallery Image!",
    "StartAddress": 104984,
    "EndAddress": 105023,
    "MaxLength": 40
  },
  {
    "Text": "You unlocked a Secret Gallery Image!",
    "StartAddress": 105024,
    "EndAddress": 105063,
    "MaxLength": 40
  },
  {
    "Text": "You unlocked a Secret Gallery Image!",
    "StartAddress": 105064,
    "EndAddress": 105103,
    "MaxLength": 40
  },
  {
    "Text": "You unlocked a Secret Gallery Image!",
    "StartAddress": 105104,
    "EndAddress": 105143,
    "MaxLength": 40
  },
  {
    "Text": "You unlocked a NEW MODE!",
    "StartAddress": 105144,
    "EndAddress": 105175,
    "MaxLength": 32
  },
  {
    "Text": "RISKY BOOTS",
    "StartAddress": 105176,
    "EndAddress": 105191,
    "MaxLength": 16
  },
  {
    "Text": "Queen of the Seven Seas",
    "StartAddress": 105192,
    "EndAddress": 105215,
    "MaxLength": 24
  },
  {
    "Text": "WATER LILY SIREN",
    "StartAddress": 105216,
    "EndAddress": 105239,
    "MaxLength": 24
  },
  {
    "Text": "Sunbathing Seaweed",
    "StartAddress": 105240,
    "EndAddress": 105263,
    "MaxLength": 24
  },
  {
    "Text": "TUBEWORM SIREN",
    "StartAddress": 105264,
    "EndAddress": 105279,
    "MaxLength": 16
  },
  {
    "Text": "Parasite Petting Princess",
    "StartAddress": 105280,
    "EndAddress": 105311,
    "MaxLength": 32
  },
  {
    "Text": "OCTO SIREN",
    "StartAddress": 105312,
    "EndAddress": 105327,
    "MaxLength": 16
  },
  {
    "Text": "Eight Times the Terror",
    "StartAddress": 105328,
    "EndAddress": 105351,
    "MaxLength": 24
  },
  {
    "Text": "CORAL SIREN",
    "StartAddress": 105352,
    "EndAddress": 105367,
    "MaxLength": 16
  },
  {
    "Text": "Drills to the Gills ",
    "StartAddress": 105368,
    "EndAddress": 105391,
    "MaxLength": 24
  },
  {
    "Text": "ANGLER FISH SIREN",
    "StartAddress": 105392,
    "EndAddress": 105415,
    "MaxLength": 24
  },
  {
    "Text": "Deep Sea Creep",
    "StartAddress": 105416,
    "EndAddress": 105431,
    "MaxLength": 16
  },
  {
    "Text": "EMPRESS SIREN",
    "StartAddress": 105432,
    "EndAddress": 105447,
    "MaxLength": 16
  },
  {
    "Text": "The Seventh Siren",
    "StartAddress": 105448,
    "EndAddress": 105471,
    "MaxLength": 24
  },
  {
    "Text": "ULTRA EMPRESS SIREN",
    "StartAddress": 105472,
    "EndAddress": 105495,
    "MaxLength": 24
  },
  {
    "Text": "Queen of the Seven Sirens",
    "StartAddress": 105496,
    "EndAddress": 105527,
    "MaxLength": 32
  },
  {
    "Text": "Risky Boots!",
    "StartAddress": 105528,
    "EndAddress": 105543,
    "MaxLength": 16
  },
  {
    "Text": "Defeat",
    "StartAddress": 105544,
    "EndAddress": 105551,
    "MaxLength": 8
  },
  {
    "Text": "Arena Town",
    "StartAddress": 105552,
    "EndAddress": 105567,
    "MaxLength": 16
  },
  {
    "Text": "Armor Town",
    "StartAddress": 105568,
    "EndAddress": 105583,
    "MaxLength": 16
  },
  {
    "Text": "Deep Sea Domain",
    "StartAddress": 105584,
    "EndAddress": 105599,
    "MaxLength": 16
  },
  {
    "Text": "Sunken Shipyard",
    "StartAddress": 105600,
    "EndAddress": 105615,
    "MaxLength": 16
  },
  {
    "Text": "Mining Site",
    "StartAddress": 105616,
    "EndAddress": 105631,
    "MaxLength": 16
  },
  {
    "Text": "Mossy Biome",
    "StartAddress": 105632,
    "EndAddress": 105647,
    "MaxLength": 16
  },
  {
    "Text": "Laboratory",
    "StartAddress": 105648,
    "EndAddress": 105663,
    "MaxLength": 16
  },
  {
    "Text": "Service Area",
    "StartAddress": 105664,
    "EndAddress": 105679,
    "MaxLength": 16
  },
  {
    "Text": "Tour Route",
    "StartAddress": 105680,
    "EndAddress": 105695,
    "MaxLength": 16
  },
  {
    "Text": "Water Lily's Den",
    "StartAddress": 105696,
    "EndAddress": 105719,
    "MaxLength": 24
  },
  {
    "Text": "Coral Mine",
    "StartAddress": 105720,
    "EndAddress": 105735,
    "MaxLength": 16
  },
  {
    "Text": "Sea Vent Lab",
    "StartAddress": 105736,
    "EndAddress": 105751,
    "MaxLength": 16
  },
  {
    "Text": "The Boiler",
    "StartAddress": 105752,
    "EndAddress": 105767,
    "MaxLength": 16
  },
  {
    "Text": "Squid Pit",
    "StartAddress": 105768,
    "EndAddress": 105783,
    "MaxLength": 16
  },
  {
    "Text": "Flying Fortress",
    "StartAddress": 105784,
    "EndAddress": 105799,
    "MaxLength": 16
  },
  {
    "Text": "Island West",
    "StartAddress": 105800,
    "EndAddress": 105815,
    "MaxLength": 16
  },
  {
    "Text": "Island East",
    "StartAddress": 105816,
    "EndAddress": 105831,
    "MaxLength": 16
  },
  {
    "Text": "Tree Town",
    "StartAddress": 105832,
    "EndAddress": 105847,
    "MaxLength": 16
  },
  {
    "Text": "Part 1 Complete!",
    "StartAddress": 105848,
    "EndAddress": 105871,
    "MaxLength": 24
  },
  {
    "Text": "Tree Town",
    "StartAddress": 105872,
    "EndAddress": 105887,
    "MaxLength": 16
  },
  {
    "Text": "Energy Collector Mk. 1",
    "StartAddress": 105888,
    "EndAddress": 105911,
    "MaxLength": 24
  },
  {
    "Text": "Sun Siphoning Silo",
    "StartAddress": 105912,
    "EndAddress": 105935,
    "MaxLength": 24
  },
  {
    "Text": "Energy Collector Mk. 2",
    "StartAddress": 105936,
    "EndAddress": 105959,
    "MaxLength": 24
  },
  {
    "Text": "Sun Siphoning Silo",
    "StartAddress": 105960,
    "EndAddress": 105983,
    "MaxLength": 24
  },
  {
    "Text": "Energy Collector Mk. 3",
    "StartAddress": 105984,
    "EndAddress": 106007,
    "MaxLength": 24
  },
  {
    "Text": "Sun Siphoning Silo",
    "StartAddress": 106008,
    "EndAddress": 106031,
    "MaxLength": 24
  },
  {
    "Text": "Energy Collector Mk. 4",
    "StartAddress": 106032,
    "EndAddress": 106055,
    "MaxLength": 24
  },
  {
    "Text": "Sun Siphoning Silo",
    "StartAddress": 106056,
    "EndAddress": 106079,
    "MaxLength": 24
  },
  {
    "Text": "Opening Sequence",
    "StartAddress": 106080,
    "EndAddress": 106103,
    "MaxLength": 24
  },
  {
    "Text": "Arriving at the Island",
    "StartAddress": 106104,
    "EndAddress": 106127,
    "MaxLength": 24
  },
  {
    "Text": "Trouble on Stage",
    "StartAddress": 106128,
    "EndAddress": 106151,
    "MaxLength": 24
  },
  {
    "Text": "Falling into the City",
    "StartAddress": 106152,
    "EndAddress": 106175,
    "MaxLength": 24
  },
  {
    "Text": "Water Lily Siren",
    "StartAddress": 106176,
    "EndAddress": 106199,
    "MaxLength": 24
  },
  {
    "Text": "Coral Siren",
    "StartAddress": 106200,
    "EndAddress": 106215,
    "MaxLength": 16
  },
  {
    "Text": "Tubeworm Siren",
    "StartAddress": 106216,
    "EndAddress": 106231,
    "MaxLength": 16
  },
  {
    "Text": "Angler Fish Siren",
    "StartAddress": 106232,
    "EndAddress": 106255,
    "MaxLength": 24
  },
  {
    "Text": "Octo Siren",
    "StartAddress": 106256,
    "EndAddress": 106271,
    "MaxLength": 16
  },
  {
    "Text": "Towers Rising",
    "StartAddress": 106272,
    "EndAddress": 106287,
    "MaxLength": 16
  },
  {
    "Text": "Lift Off",
    "StartAddress": 106288,
    "EndAddress": 106303,
    "MaxLength": 16
  },
  {
    "Text": "Falling to Pieces",
    "StartAddress": 106304,
    "EndAddress": 106327,
    "MaxLength": 24
  },
  {
    "Text": "Fond Farewells",
    "StartAddress": 106328,
    "EndAddress": 106343,
    "MaxLength": 16
  },
  {
    "Text": "Save Data",
    "StartAddress": 106344,
    "EndAddress": 106359,
    "MaxLength": 16
  },
  {
    "Text": "Controller has been disconnected.",
    "StartAddress": 106360,
    "EndAddress": 106399,
    "MaxLength": 40
  },
  {
    "Text": "Please re-connect the controller.",
    "StartAddress": 106400,
    "EndAddress": 106439,
    "MaxLength": 40
  },
  {
    "Text": "Paradise Island",
    "StartAddress": 106440,
    "EndAddress": 106455,
    "MaxLength": 16
  },
  {
    "Text": "Warp back to Arena Town?",
    "StartAddress": 106456,
    "EndAddress": 106487,
    "MaxLength": 32
  },
  {
    "Text": "Zapple is waiting in Armor Town for one of these!",
    "StartAddress": 106488,
    "EndAddress": 106543,
    "MaxLength": 56
  },
  {
    "Text": "Harmony was looking for one of these!",
    "StartAddress": 106544,
    "EndAddress": 106583,
    "MaxLength": 40
  },
  {
    "Text": "Triple Fireball",
    "StartAddress": 106584,
    "EndAddress": 106599,
    "MaxLength": 16
  },
  {
    "Text": "Super Pike Ball",
    "StartAddress": 106600,
    "EndAddress": 106615,
    "MaxLength": 16
  },
  {
    "Text": "Homing Rocket 1",
    "StartAddress": 106616,
    "EndAddress": 106631,
    "MaxLength": 16
  },
  {
    "Text": "Homing Rocket 2",
    "StartAddress": 106632,
    "EndAddress": 106647,
    "MaxLength": 16
  },
  {
    "Text": "Homing Rocket 3",
    "StartAddress": 106648,
    "EndAddress": 106663,
    "MaxLength": 16
  },
  {
    "Text": "Super Silky Cream",
    "StartAddress": 106664,
    "EndAddress": 106687,
    "MaxLength": 24
  },
  {
    "Text": "Mega Silky Cream",
    "StartAddress": 106688,
    "EndAddress": 106711,
    "MaxLength": 24
  },
  {
    "Text": "Double Boomerang",
    "StartAddress": 106712,
    "EndAddress": 106735,
    "MaxLength": 24
  },
  {
    "Text": "Triple Boomerang",
    "StartAddress": 106736,
    "EndAddress": 106759,
    "MaxLength": 24
  },
  {
    "Text": "Max Attract",
    "StartAddress": 106760,
    "EndAddress": 106775,
    "MaxLength": 16
  },
  {
    "Text": "MP Saver",
    "StartAddress": 106776,
    "EndAddress": 106791,
    "MaxLength": 16
  },
  {
    "Text": "Ultra",
    "StartAddress": 106792,
    "EndAddress": 106799,
    "MaxLength": 8
  },
  {
    "Text": "Magical!",
    "StartAddress": 106800,
    "EndAddress": 106815,
    "MaxLength": 16
  },
  {
    "Text": "Complete the game in new game plus.",
    "StartAddress": 106816,
    "EndAddress": 106855,
    "MaxLength": 40
  },
  {
    "Text": "You unlocked a Secret Gallery Image!",
    "StartAddress": 106856,
    "EndAddress": 106895,
    "MaxLength": 40
  },
  {
    "Text": "Bonus image - New Game Plus!",
    "StartAddress": 106896,
    "EndAddress": 106927,
    "MaxLength": 32
  },
  {
    "Text": "Tap to Continue",
    "StartAddress": 106928,
    "EndAddress": 106943,
    "MaxLength": 16
  },
  {
    "Text": "No Game Center account",
    "StartAddress": 106976,
    "EndAddress": 106999,
    "MaxLength": 24
  }
]